{"nodes": [{"id": "modules_ocr_pororo_pororo_models_brainocr_model_py", "label": "model.py", "file_type": "code", "source_file": "modules\\ocr\\pororo\\pororo\\models\\brainOCR\\model.py", "source_location": "L1"}, {"id": "model_model", "label": "Model", "file_type": "code", "source_file": "modules\\ocr\\pororo\\pororo\\models\\brainOCR\\model.py", "source_location": "L18"}, {"id": "model_model_init", "label": ".__init__()", "file_type": "code", "source_file": "modules\\ocr\\pororo\\pororo\\models\\brainOCR\\model.py", "source_location": "L20"}, {"id": "model_model_forward", "label": ".forward()", "file_type": "code", "source_file": "modules\\ocr\\pororo\\pororo\\models\\brainOCR\\model.py", "source_location": "L96"}, {"id": "model_rationale_1", "label": "This code is adapted from https://github.com/clovaai/deep-text-recognition-benc", "file_type": "rationale", "source_file": "modules\\ocr\\pororo\\pororo\\models\\brainOCR\\model.py", "source_location": "L1"}, {"id": "model_rationale_97", "label": ":param x: (batch, input_channel, height, width)         :return:", "file_type": "rationale", "source_file": "modules\\ocr\\pororo\\pororo\\models\\brainOCR\\model.py", "source_location": "L97"}], "edges": [{"source": "modules_ocr_pororo_pororo_models_brainocr_model_py", "target": "torch_nn", "relation": "imports", "confidence": "EXTRACTED", "source_file": "modules\\ocr\\pororo\\pororo\\models\\brainOCR\\model.py", "source_location": "L6", "weight": 1.0}, {"source": "modules_ocr_pororo_pororo_models_brainocr_model_py", "target": "torch", "relation": "imports_from", "confidence": "EXTRACTED", "source_file": "modules\\ocr\\pororo\\pororo\\models\\brainOCR\\model.py", "source_location": "L7", "weight": 1.0}, {"source": "modules_ocr_pororo_pororo_models_brainocr_model_py", "target": "modules_ocr_pororo_pororo_models_brainocr_modules_feature_extraction_py", "relation": "imports_from", "confidence": "EXTRACTED", "source_file": "modules\\ocr\\pororo\\pororo\\models\\brainOCR\\model.py", "source_location": "L9", "weight": 1.0}, {"source": "modules_ocr_pororo_pororo_models_brainocr_model_py", "target": "modules_ocr_pororo_pororo_models_brainocr_modules_prediction_py", "relation": "imports_from", "confidence": "EXTRACTED", "source_file": "modules\\ocr\\pororo\\pororo\\models\\brainOCR\\model.py", "source_location": "L13", "weight": 1.0}, {"source": "modules_ocr_pororo_pororo_models_brainocr_model_py", "target": "modules_ocr_pororo_pororo_models_brainocr_modules_sequence_modeling_py", "relation": "imports_from", "confidence": "EXTRACTED", "source_file": "modules\\ocr\\pororo\\pororo\\models\\brainOCR\\model.py", "source_location": "L14", "weight": 1.0}, {"source": "modules_ocr_pororo_pororo_models_brainocr_model_py", "target": "modules_ocr_pororo_pororo_models_brainocr_modules_transformation_py", "relation": "imports_from", "confidence": "EXTRACTED", "source_file": "modules\\ocr\\pororo\\pororo\\models\\brainOCR\\model.py", "source_location": "L15", "weight": 1.0}, {"source": "modules_ocr_pororo_pororo_models_brainocr_model_py", "target": "model_model", "relation": "contains", "confidence": "EXTRACTED", "source_file": "modules\\ocr\\pororo\\pororo\\models\\brainOCR\\model.py", "source_location": "L18", "weight": 1.0}, {"source": "model_model", "target": "model_model_init", "relation": "method", "confidence": "EXTRACTED", "source_file": "modules\\ocr\\pororo\\pororo\\models\\brainOCR\\model.py", "source_location": "L20", "weight": 1.0}, {"source": "model_model", "target": "model_model_forward", "relation": "method", "confidence": "EXTRACTED", "source_file": "modules\\ocr\\pororo\\pororo\\models\\brainOCR\\model.py", "source_location": "L96", "weight": 1.0}, {"source": "model_rationale_1", "target": "modules_ocr_pororo_pororo_models_brainocr_model_py", "relation": "rationale_for", "confidence": "EXTRACTED", "source_file": "modules\\ocr\\pororo\\pororo\\models\\brainOCR\\model.py", "source_location": "L1", "weight": 1.0}, {"source": "model_rationale_97", "target": "model_model_forward", "relation": "rationale_for", "confidence": "EXTRACTED", "source_file": "modules\\ocr\\pororo\\pororo\\models\\brainOCR\\model.py", "source_location": "L97", "weight": 1.0}], "raw_calls": [{"caller_nid": "model_model_init", "callee": "super", "source_file": "modules\\ocr\\pororo\\pororo\\models\\brainOCR\\model.py", "source_location": "L21"}, {"caller_nid": "model_model_init", "callee": "TpsSpatialTransformerNetwork", "source_file": "modules\\ocr\\pororo\\pororo\\models\\brainOCR\\model.py", "source_location": "L37"}, {"caller_nid": "model_model_init", "callee": "print", "source_file": "modules\\ocr\\pororo\\pororo\\models\\brainOCR\\model.py", "source_location": "L44"}, {"caller_nid": "model_model_init", "callee": "extractor", "source_file": "modules\\ocr\\pororo\\pororo\\models\\brainOCR\\model.py", "source_location": "L51"}, {"caller_nid": "model_model_init", "callee": "Sequential", "source_file": "modules\\ocr\\pororo\\pororo\\models\\brainOCR\\model.py", "source_location": "L66"}, {"caller_nid": "model_model_init", "callee": "BidirectionalLSTM", "source_file": "modules\\ocr\\pororo\\pororo\\models\\brainOCR\\model.py", "source_location": "L67"}, {"caller_nid": "model_model_init", "callee": "BidirectionalLSTM", "source_file": "modules\\ocr\\pororo\\pororo\\models\\brainOCR\\model.py", "source_location": "L72"}, {"caller_nid": "model_model_init", "callee": "print", "source_file": "modules\\ocr\\pororo\\pororo\\models\\brainOCR\\model.py", "source_location": "L76"}, {"caller_nid": "model_model_init", "callee": "Linear", "source_file": "modules\\ocr\\pororo\\pororo\\models\\brainOCR\\model.py", "source_location": "L81"}, {"caller_nid": "model_model_init", "callee": "Attention", "source_file": "modules\\ocr\\pororo\\pororo\\models\\brainOCR\\model.py", "source_location": "L86"}, {"caller_nid": "model_model_init", "callee": "Exception", "source_file": "modules\\ocr\\pororo\\pororo\\models\\brainOCR\\model.py", "source_location": "L94"}, {"caller_nid": "model_model_forward", "callee": "Transformation", "source_file": "modules\\ocr\\pororo\\pororo\\models\\brainOCR\\model.py", "source_location": "L102"}, {"caller_nid": "model_model_forward", "callee": "FeatureExtraction", "source_file": "modules\\ocr\\pororo\\pororo\\models\\brainOCR\\model.py", "source_location": "L105"}, {"caller_nid": "model_model_forward", "callee": "mean", "source_file": "modules\\ocr\\pororo\\pororo\\models\\brainOCR\\model.py", "source_location": "L109"}, {"caller_nid": "model_model_forward", "callee": "permute", "source_file": "modules\\ocr\\pororo\\pororo\\models\\brainOCR\\model.py", "source_location": "L110"}, {"caller_nid": "model_model_forward", "callee": "eval", "source_file": "modules\\ocr\\pororo\\pororo\\models\\brainOCR\\model.py", "source_location": "L113"}, {"caller_nid": "model_model_forward", "callee": "SequenceModeling", "source_file": "modules\\ocr\\pororo\\pororo\\models\\brainOCR\\model.py", "source_location": "L114"}, {"caller_nid": "model_model_forward", "callee": "Prediction", "source_file": "modules\\ocr\\pororo\\pororo\\models\\brainOCR\\model.py", "source_location": "L117"}, {"caller_nid": "model_model_forward", "callee": "contiguous", "source_file": "modules\\ocr\\pororo\\pororo\\models\\brainOCR\\model.py", "source_location": "L118"}]}