{"nodes": [{"id": "modules_detection_text_block_builder_py", "label": "text_block_builder.py", "file_type": "code", "source_file": "modules\\detection\\text_block_builder.py", "source_location": "L1"}, {"id": "text_block_builder_detect_font_attributes", "label": "_detect_font_attributes()", "file_type": "code", "source_file": "modules\\detection\\text_block_builder.py", "source_location": "L13"}, {"id": "text_block_builder_make_text_block", "label": "_make_text_block()", "file_type": "code", "source_file": "modules\\detection\\text_block_builder.py", "source_location": "L34"}, {"id": "text_block_builder_create_text_blocks", "label": "create_text_blocks()", "file_type": "code", "source_file": "modules\\detection\\text_block_builder.py", "source_location": "L55"}], "edges": [{"source": "modules_detection_text_block_builder_py", "target": "numpy", "relation": "imports", "confidence": "EXTRACTED", "source_file": "modules\\detection\\text_block_builder.py", "source_location": "L1", "weight": 1.0}, {"source": "modules_detection_text_block_builder_py", "target": "modules_utils_textblock_py", "relation": "imports_from", "confidence": "EXTRACTED", "source_file": "modules\\detection\\text_block_builder.py", "source_location": "L3", "weight": 1.0}, {"source": "modules_detection_text_block_builder_py", "target": "modules_detection_font_engine_py", "relation": "imports_from", "confidence": "EXTRACTED", "source_file": "modules\\detection\\text_block_builder.py", "source_location": "L4", "weight": 1.0}, {"source": "modules_detection_text_block_builder_py", "target": "modules_detection_utils_content_py", "relation": "imports_from", "confidence": "EXTRACTED", "source_file": "modules\\detection\\text_block_builder.py", "source_location": "L5", "weight": 1.0}, {"source": "modules_detection_text_block_builder_py", "target": "modules_detection_utils_geometry_py", "relation": "imports_from", "confidence": "EXTRACTED", "source_file": "modules\\detection\\text_block_builder.py", "source_location": "L6", "weight": 1.0}, {"source": "modules_detection_text_block_builder_py", "target": "text_block_builder_detect_font_attributes", "relation": "contains", "confidence": "EXTRACTED", "source_file": "modules\\detection\\text_block_builder.py", "source_location": "L13", "weight": 1.0}, {"source": "modules_detection_text_block_builder_py", "target": "text_block_builder_make_text_block", "relation": "contains", "confidence": "EXTRACTED", "source_file": "modules\\detection\\text_block_builder.py", "source_location": "L34", "weight": 1.0}, {"source": "modules_detection_text_block_builder_py", "target": "text_block_builder_create_text_blocks", "relation": "contains", "confidence": "EXTRACTED", "source_file": "modules\\detection\\text_block_builder.py", "source_location": "L55", "weight": 1.0}, {"source": "text_block_builder_create_text_blocks", "target": "text_block_builder_detect_font_attributes", "relation": "calls", "confidence": "EXTRACTED", "source_file": "modules\\detection\\text_block_builder.py", "source_location": "L72", "weight": 1.0}, {"source": "text_block_builder_create_text_blocks", "target": "text_block_builder_make_text_block", "relation": "calls", "confidence": "EXTRACTED", "source_file": "modules\\detection\\text_block_builder.py", "source_location": "L76", "weight": 1.0}], "raw_calls": [{"caller_nid": "text_block_builder_detect_font_attributes", "callee": "map", "source_file": "modules\\detection\\text_block_builder.py", "source_location": "L17"}, {"caller_nid": "text_block_builder_detect_font_attributes", "callee": "max", "source_file": "modules\\detection\\text_block_builder.py", "source_location": "L19"}, {"caller_nid": "text_block_builder_detect_font_attributes", "callee": "max", "source_file": "modules\\detection\\text_block_builder.py", "source_location": "L20"}, {"caller_nid": "text_block_builder_detect_font_attributes", "callee": "min", "source_file": "modules\\detection\\text_block_builder.py", "source_location": "L21"}, {"caller_nid": "text_block_builder_detect_font_attributes", "callee": "min", "source_file": "modules\\detection\\text_block_builder.py", "source_location": "L22"}, {"caller_nid": "text_block_builder_detect_font_attributes", "callee": "create_engine", "source_file": "modules\\detection\\text_block_builder.py", "source_location": "L26"}, {"caller_nid": "text_block_builder_detect_font_attributes", "callee": "process", "source_file": "modules\\detection\\text_block_builder.py", "source_location": "L27"}, {"caller_nid": "text_block_builder_detect_font_attributes", "callee": "print", "source_file": "modules\\detection\\text_block_builder.py", "source_location": "L29"}, {"caller_nid": "text_block_builder_make_text_block", "callee": "float", "source_file": "modules\\detection\\text_block_builder.py", "source_location": "L42"}, {"caller_nid": "text_block_builder_make_text_block", "callee": "get", "source_file": "modules\\detection\\text_block_builder.py", "source_location": "L42"}, {"caller_nid": "text_block_builder_make_text_block", "callee": "TextBlock", "source_file": "modules\\detection\\text_block_builder.py", "source_location": "L44"}, {"caller_nid": "text_block_builder_make_text_block", "callee": "get", "source_file": "modules\\detection\\text_block_builder.py", "source_location": "L48"}, {"caller_nid": "text_block_builder_make_text_block", "callee": "tuple", "source_file": "modules\\detection\\text_block_builder.py", "source_location": "L49"}, {"caller_nid": "text_block_builder_make_text_block", "callee": "get", "source_file": "modules\\detection\\text_block_builder.py", "source_location": "L49"}, {"caller_nid": "text_block_builder_make_text_block", "callee": "int", "source_file": "modules\\detection\\text_block_builder.py", "source_location": "L51"}, {"caller_nid": "text_block_builder_make_text_block", "callee": "round", "source_file": "modules\\detection\\text_block_builder.py", "source_location": "L51"}, {"caller_nid": "text_block_builder_create_text_blocks", "callee": "filter_and_fix_bboxes", "source_file": "modules\\detection\\text_block_builder.py", "source_location": "L61"}, {"caller_nid": "text_block_builder_create_text_blocks", "callee": "empty", "source_file": "modules\\detection\\text_block_builder.py", "source_location": "L63"}, {"caller_nid": "text_block_builder_create_text_blocks", "callee": "filter_and_fix_bboxes", "source_file": "modules\\detection\\text_block_builder.py", "source_location": "L65"}, {"caller_nid": "text_block_builder_create_text_blocks", "callee": "merge_overlapping_boxes", "source_file": "modules\\detection\\text_block_builder.py", "source_location": "L66"}, {"caller_nid": "text_block_builder_create_text_blocks", "callee": "len", "source_file": "modules\\detection\\text_block_builder.py", "source_location": "L69"}, {"caller_nid": "text_block_builder_create_text_blocks", "callee": "enumerate", "source_file": "modules\\detection\\text_block_builder.py", "source_location": "L71"}, {"caller_nid": "text_block_builder_create_text_blocks", "callee": "len", "source_file": "modules\\detection\\text_block_builder.py", "source_location": "L74"}, {"caller_nid": "text_block_builder_create_text_blocks", "callee": "append", "source_file": "modules\\detection\\text_block_builder.py", "source_location": "L75"}, {"caller_nid": "text_block_builder_create_text_blocks", "callee": "does_rectangle_fit", "source_file": "modules\\detection\\text_block_builder.py", "source_location": "L83"}, {"caller_nid": "text_block_builder_create_text_blocks", "callee": "do_rectangles_overlap", "source_file": "modules\\detection\\text_block_builder.py", "source_location": "L83"}, {"caller_nid": "text_block_builder_create_text_blocks", "callee": "append", "source_file": "modules\\detection\\text_block_builder.py", "source_location": "L84"}, {"caller_nid": "text_block_builder_create_text_blocks", "callee": "append", "source_file": "modules\\detection\\text_block_builder.py", "source_location": "L96"}]}