{"nodes": [{"id": "app_ui_canvas_webtoons_webtoon_layout_manager_py", "label": "webtoon_layout_manager.py", "file_type": "code", "source_file": "app\\ui\\canvas\\webtoons\\webtoon_layout_manager.py", "source_location": "L1"}, {"id": "webtoon_layout_manager_webtoonlayoutmanager", "label": "WebtoonLayoutManager", "file_type": "code", "source_file": "app\\ui\\canvas\\webtoons\\webtoon_layout_manager.py", "source_location": "L12"}, {"id": "webtoon_layout_manager_webtoonlayoutmanager_init", "label": ".__init__()", "file_type": "code", "source_file": "app\\ui\\canvas\\webtoons\\webtoon_layout_manager.py", "source_location": "L15"}, {"id": "webtoon_layout_manager_webtoonlayoutmanager_estimate_layout", "label": ".estimate_layout()", "file_type": "code", "source_file": "app\\ui\\canvas\\webtoons\\webtoon_layout_manager.py", "source_location": "L45"}, {"id": "webtoon_layout_manager_webtoonlayoutmanager_adjust_layout_for_actual_size", "label": ".adjust_layout_for_actual_size()", "file_type": "code", "source_file": "app\\ui\\canvas\\webtoons\\webtoon_layout_manager.py", "source_location": "L94"}, {"id": "webtoon_layout_manager_webtoonlayoutmanager_get_visible_pages", "label": ".get_visible_pages()", "file_type": "code", "source_file": "app\\ui\\canvas\\webtoons\\webtoon_layout_manager.py", "source_location": "L118"}, {"id": "webtoon_layout_manager_webtoonlayoutmanager_get_pages_for_scene_bounds", "label": ".get_pages_for_scene_bounds()", "file_type": "code", "source_file": "app\\ui\\canvas\\webtoons\\webtoon_layout_manager.py", "source_location": "L139"}, {"id": "webtoon_layout_manager_webtoonlayoutmanager_get_page_at_position", "label": ".get_page_at_position()", "file_type": "code", "source_file": "app\\ui\\canvas\\webtoons\\webtoon_layout_manager.py", "source_location": "L154"}, {"id": "webtoon_layout_manager_webtoonlayoutmanager_scroll_to_page", "label": ".scroll_to_page()", "file_type": "code", "source_file": "app\\ui\\canvas\\webtoons\\webtoon_layout_manager.py", "source_location": "L161"}, {"id": "webtoon_layout_manager_webtoonlayoutmanager_update_current_page", "label": ".update_current_page()", "file_type": "code", "source_file": "app\\ui\\canvas\\webtoons\\webtoon_layout_manager.py", "source_location": "L200"}, {"id": "webtoon_layout_manager_webtoonlayoutmanager_update_page_on_click", "label": ".update_page_on_click()", "file_type": "code", "source_file": "app\\ui\\canvas\\webtoons\\webtoon_layout_manager.py", "source_location": "L245"}, {"id": "webtoon_layout_manager_webtoonlayoutmanager_ensure_current_page_visible", "label": ".ensure_current_page_visible()", "file_type": "code", "source_file": "app\\ui\\canvas\\webtoons\\webtoon_layout_manager.py", "source_location": "L253"}, {"id": "webtoon_layout_manager_webtoonlayoutmanager_enable_page_detection_after_delay", "label": ".enable_page_detection_after_delay()", "file_type": "code", "source_file": "app\\ui\\canvas\\webtoons\\webtoon_layout_manager.py", "source_location": "L274"}, {"id": "webtoon_layout_manager_webtoonlayoutmanager_enable_page_detection", "label": "._enable_page_detection()", "file_type": "code", "source_file": "app\\ui\\canvas\\webtoons\\webtoon_layout_manager.py", "source_location": "L278"}, {"id": "webtoon_layout_manager_webtoonlayoutmanager_set_page_detection_delay", "label": ".set_page_detection_delay()", "file_type": "code", "source_file": "app\\ui\\canvas\\webtoons\\webtoon_layout_manager.py", "source_location": "L286"}, {"id": "webtoon_layout_manager_webtoonlayoutmanager_get_page_detection_delay", "label": ".get_page_detection_delay()", "file_type": "code", "source_file": "app\\ui\\canvas\\webtoons\\webtoon_layout_manager.py", "source_location": "L291"}, {"id": "webtoon_layout_manager_webtoonlayoutmanager_disable_page_detection", "label": ".disable_page_detection()", "file_type": "code", "source_file": "app\\ui\\canvas\\webtoons\\webtoon_layout_manager.py", "source_location": "L295"}, {"id": "webtoon_layout_manager_webtoonlayoutmanager_scene_to_page_coordinates", "label": ".scene_to_page_coordinates()", "file_type": "code", "source_file": "app\\ui\\canvas\\webtoons\\webtoon_layout_manager.py", "source_location": "L300"}, {"id": "webtoon_layout_manager_webtoonlayoutmanager_page_to_scene_coordinates", "label": ".page_to_scene_coordinates()", "file_type": "code", "source_file": "app\\ui\\canvas\\webtoons\\webtoon_layout_manager.py", "source_location": "L311"}, {"id": "webtoon_layout_manager_webtoonlayoutmanager_clear", "label": ".clear()", "file_type": "code", "source_file": "app\\ui\\canvas\\webtoons\\webtoon_layout_manager.py", "source_location": "L322"}, {"id": "webtoon_layout_manager_webtoonlayoutmanager_recalculate_layout", "label": "._recalculate_layout()", "file_type": "code", "source_file": "app\\ui\\canvas\\webtoons\\webtoon_layout_manager.py", "source_location": "L332"}, {"id": "webtoon_layout_manager_rationale_1", "label": "Webtoon Layout Manager  Handles layout calculations, positioning, and viewport", "file_type": "rationale", "source_file": "app\\ui\\canvas\\webtoons\\webtoon_layout_manager.py", "source_location": "L1"}, {"id": "webtoon_layout_manager_rationale_13", "label": "Manages layout and viewport calculations for webtoon mode.", "file_type": "rationale", "source_file": "app\\ui\\canvas\\webtoons\\webtoon_layout_manager.py", "source_location": "L13"}, {"id": "webtoon_layout_manager_rationale_46", "label": "Estimate layout dimensions without loading all images.", "file_type": "rationale", "source_file": "app\\ui\\canvas\\webtoons\\webtoon_layout_manager.py", "source_location": "L46"}, {"id": "webtoon_layout_manager_rationale_95", "label": "Adjust layout when actual image dimensions differ from estimates.", "file_type": "rationale", "source_file": "app\\ui\\canvas\\webtoons\\webtoon_layout_manager.py", "source_location": "L95"}, {"id": "webtoon_layout_manager_rationale_119", "label": "Get pages currently visible in viewport + buffer.", "file_type": "rationale", "source_file": "app\\ui\\canvas\\webtoons\\webtoon_layout_manager.py", "source_location": "L119"}, {"id": "webtoon_layout_manager_rationale_140", "label": "Get all pages that a scene rectangle intersects with.", "file_type": "rationale", "source_file": "app\\ui\\canvas\\webtoons\\webtoon_layout_manager.py", "source_location": "L140"}, {"id": "webtoon_layout_manager_rationale_155", "label": "Get the page index at a given Y position.", "file_type": "rationale", "source_file": "app\\ui\\canvas\\webtoons\\webtoon_layout_manager.py", "source_location": "L155"}, {"id": "webtoon_layout_manager_rationale_162", "label": "Scroll to a specific page.", "file_type": "rationale", "source_file": "app\\ui\\canvas\\webtoons\\webtoon_layout_manager.py", "source_location": "L162"}, {"id": "webtoon_layout_manager_rationale_201", "label": "Update current page index based on viewport center. Returns True if page changed", "file_type": "rationale", "source_file": "app\\ui\\canvas\\webtoons\\webtoon_layout_manager.py", "source_location": "L201"}, {"id": "webtoon_layout_manager_rationale_246", "label": "Check if a click occurred on a new page and update current page. Returns True if", "file_type": "rationale", "source_file": "app\\ui\\canvas\\webtoons\\webtoon_layout_manager.py", "source_location": "L246"}, {"id": "webtoon_layout_manager_rationale_254", "label": "Ensure the current page is visible and view is properly set up.", "file_type": "rationale", "source_file": "app\\ui\\canvas\\webtoons\\webtoon_layout_manager.py", "source_location": "L254"}, {"id": "webtoon_layout_manager_rationale_275", "label": "Enable page detection after a delay to let viewport settle.", "file_type": "rationale", "source_file": "app\\ui\\canvas\\webtoons\\webtoon_layout_manager.py", "source_location": "L275"}, {"id": "webtoon_layout_manager_rationale_279", "label": "Enable page detection after initialization is complete.", "file_type": "rationale", "source_file": "app\\ui\\canvas\\webtoons\\webtoon_layout_manager.py", "source_location": "L279"}, {"id": "webtoon_layout_manager_rationale_287", "label": "Set the page detection timer delay.", "file_type": "rationale", "source_file": "app\\ui\\canvas\\webtoons\\webtoon_layout_manager.py", "source_location": "L287"}, {"id": "webtoon_layout_manager_rationale_292", "label": "Get the current page detection timer delay.", "file_type": "rationale", "source_file": "app\\ui\\canvas\\webtoons\\webtoon_layout_manager.py", "source_location": "L292"}, {"id": "webtoon_layout_manager_rationale_296", "label": "Disable page detection.", "file_type": "rationale", "source_file": "app\\ui\\canvas\\webtoons\\webtoon_layout_manager.py", "source_location": "L296"}, {"id": "webtoon_layout_manager_rationale_301", "label": "Convert scene coordinates to page-local coordinates.", "file_type": "rationale", "source_file": "app\\ui\\canvas\\webtoons\\webtoon_layout_manager.py", "source_location": "L301"}, {"id": "webtoon_layout_manager_rationale_312", "label": "Convert page-local coordinates to scene coordinates.", "file_type": "rationale", "source_file": "app\\ui\\canvas\\webtoons\\webtoon_layout_manager.py", "source_location": "L312"}, {"id": "webtoon_layout_manager_rationale_323", "label": "Clear all layout state.", "file_type": "rationale", "source_file": "app\\ui\\canvas\\webtoons\\webtoon_layout_manager.py", "source_location": "L323"}, {"id": "webtoon_layout_manager_rationale_333", "label": "Recalculate layout positions after page addition/removal.", "file_type": "rationale", "source_file": "app\\ui\\canvas\\webtoons\\webtoon_layout_manager.py", "source_location": "L333"}], "edges": [{"source": "app_ui_canvas_webtoons_webtoon_layout_manager_py", "target": "typing", "relation": "imports_from", "confidence": "EXTRACTED", "source_file": "app\\ui\\canvas\\webtoons\\webtoon_layout_manager.py", "source_location": "L8", "weight": 1.0}, {"source": "app_ui_canvas_webtoons_webtoon_layout_manager_py", "target": "pyside6_qtcore", "relation": "imports_from", "confidence": "EXTRACTED", "source_file": "app\\ui\\canvas\\webtoons\\webtoon_layout_manager.py", "source_location": "L9", "weight": 1.0}, {"source": "app_ui_canvas_webtoons_webtoon_layout_manager_py", "target": "webtoon_layout_manager_webtoonlayoutmanager", "relation": "contains", "confidence": "EXTRACTED", "source_file": "app\\ui\\canvas\\webtoons\\webtoon_layout_manager.py", "source_location": "L12", "weight": 1.0}, {"source": "webtoon_layout_manager_webtoonlayoutmanager", "target": "webtoon_layout_manager_webtoonlayoutmanager_init", "relation": "method", "confidence": "EXTRACTED", "source_file": "app\\ui\\canvas\\webtoons\\webtoon_layout_manager.py", "source_location": "L15", "weight": 1.0}, {"source": "webtoon_layout_manager_webtoonlayoutmanager", "target": "webtoon_layout_manager_webtoonlayoutmanager_estimate_layout", "relation": "method", "confidence": "EXTRACTED", "source_file": "app\\ui\\canvas\\webtoons\\webtoon_layout_manager.py", "source_location": "L45", "weight": 1.0}, {"source": "webtoon_layout_manager_webtoonlayoutmanager", "target": "webtoon_layout_manager_webtoonlayoutmanager_adjust_layout_for_actual_size", "relation": "method", "confidence": "EXTRACTED", "source_file": "app\\ui\\canvas\\webtoons\\webtoon_layout_manager.py", "source_location": "L94", "weight": 1.0}, {"source": "webtoon_layout_manager_webtoonlayoutmanager", "target": "webtoon_layout_manager_webtoonlayoutmanager_get_visible_pages", "relation": "method", "confidence": "EXTRACTED", "source_file": "app\\ui\\canvas\\webtoons\\webtoon_layout_manager.py", "source_location": "L118", "weight": 1.0}, {"source": "webtoon_layout_manager_webtoonlayoutmanager", "target": "webtoon_layout_manager_webtoonlayoutmanager_get_pages_for_scene_bounds", "relation": "method", "confidence": "EXTRACTED", "source_file": "app\\ui\\canvas\\webtoons\\webtoon_layout_manager.py", "source_location": "L139", "weight": 1.0}, {"source": "webtoon_layout_manager_webtoonlayoutmanager", "target": "webtoon_layout_manager_webtoonlayoutmanager_get_page_at_position", "relation": "method", "confidence": "EXTRACTED", "source_file": "app\\ui\\canvas\\webtoons\\webtoon_layout_manager.py", "source_location": "L154", "weight": 1.0}, {"source": "webtoon_layout_manager_webtoonlayoutmanager", "target": "webtoon_layout_manager_webtoonlayoutmanager_scroll_to_page", "relation": "method", "confidence": "EXTRACTED", "source_file": "app\\ui\\canvas\\webtoons\\webtoon_layout_manager.py", "source_location": "L161", "weight": 1.0}, {"source": "webtoon_layout_manager_webtoonlayoutmanager", "target": "webtoon_layout_manager_webtoonlayoutmanager_update_current_page", "relation": "method", "confidence": "EXTRACTED", "source_file": "app\\ui\\canvas\\webtoons\\webtoon_layout_manager.py", "source_location": "L200", "weight": 1.0}, {"source": "webtoon_layout_manager_webtoonlayoutmanager", "target": "webtoon_layout_manager_webtoonlayoutmanager_update_page_on_click", "relation": "method", "confidence": "EXTRACTED", "source_file": "app\\ui\\canvas\\webtoons\\webtoon_layout_manager.py", "source_location": "L245", "weight": 1.0}, {"source": "webtoon_layout_manager_webtoonlayoutmanager", "target": "webtoon_layout_manager_webtoonlayoutmanager_ensure_current_page_visible", "relation": "method", "confidence": "EXTRACTED", "source_file": "app\\ui\\canvas\\webtoons\\webtoon_layout_manager.py", "source_location": "L253", "weight": 1.0}, {"source": "webtoon_layout_manager_webtoonlayoutmanager", "target": "webtoon_layout_manager_webtoonlayoutmanager_enable_page_detection_after_delay", "relation": "method", "confidence": "EXTRACTED", "source_file": "app\\ui\\canvas\\webtoons\\webtoon_layout_manager.py", "source_location": "L274", "weight": 1.0}, {"source": "webtoon_layout_manager_webtoonlayoutmanager", "target": "webtoon_layout_manager_webtoonlayoutmanager_enable_page_detection", "relation": "method", "confidence": "EXTRACTED", "source_file": "app\\ui\\canvas\\webtoons\\webtoon_layout_manager.py", "source_location": "L278", "weight": 1.0}, {"source": "webtoon_layout_manager_webtoonlayoutmanager", "target": "webtoon_layout_manager_webtoonlayoutmanager_set_page_detection_delay", "relation": "method", "confidence": "EXTRACTED", "source_file": "app\\ui\\canvas\\webtoons\\webtoon_layout_manager.py", "source_location": "L286", "weight": 1.0}, {"source": "webtoon_layout_manager_webtoonlayoutmanager", "target": "webtoon_layout_manager_webtoonlayoutmanager_get_page_detection_delay", "relation": "method", "confidence": "EXTRACTED", "source_file": "app\\ui\\canvas\\webtoons\\webtoon_layout_manager.py", "source_location": "L291", "weight": 1.0}, {"source": "webtoon_layout_manager_webtoonlayoutmanager", "target": "webtoon_layout_manager_webtoonlayoutmanager_disable_page_detection", "relation": "method", "confidence": "EXTRACTED", "source_file": "app\\ui\\canvas\\webtoons\\webtoon_layout_manager.py", "source_location": "L295", "weight": 1.0}, {"source": "webtoon_layout_manager_webtoonlayoutmanager", "target": "webtoon_layout_manager_webtoonlayoutmanager_scene_to_page_coordinates", "relation": "method", "confidence": "EXTRACTED", "source_file": "app\\ui\\canvas\\webtoons\\webtoon_layout_manager.py", "source_location": "L300", "weight": 1.0}, {"source": "webtoon_layout_manager_webtoonlayoutmanager", "target": "webtoon_layout_manager_webtoonlayoutmanager_page_to_scene_coordinates", "relation": "method", "confidence": "EXTRACTED", "source_file": "app\\ui\\canvas\\webtoons\\webtoon_layout_manager.py", "source_location": "L311", "weight": 1.0}, {"source": "webtoon_layout_manager_webtoonlayoutmanager", "target": "webtoon_layout_manager_webtoonlayoutmanager_clear", "relation": "method", "confidence": "EXTRACTED", "source_file": "app\\ui\\canvas\\webtoons\\webtoon_layout_manager.py", "source_location": "L322", "weight": 1.0}, {"source": "webtoon_layout_manager_webtoonlayoutmanager", "target": "webtoon_layout_manager_webtoonlayoutmanager_recalculate_layout", "relation": "method", "confidence": "EXTRACTED", "source_file": "app\\ui\\canvas\\webtoons\\webtoon_layout_manager.py", "source_location": "L332", "weight": 1.0}, {"source": "webtoon_layout_manager_webtoonlayoutmanager_estimate_layout", "target": "webtoon_layout_manager_webtoonlayoutmanager_clear", "relation": "calls", "confidence": "EXTRACTED", "source_file": "app\\ui\\canvas\\webtoons\\webtoon_layout_manager.py", "source_location": "L75", "weight": 1.0}, {"source": "webtoon_layout_manager_webtoonlayoutmanager_update_page_on_click", "target": "webtoon_layout_manager_webtoonlayoutmanager_get_page_at_position", "relation": "calls", "confidence": "EXTRACTED", "source_file": "app\\ui\\canvas\\webtoons\\webtoon_layout_manager.py", "source_location": "L247", "weight": 1.0}, {"source": "webtoon_layout_manager_webtoonlayoutmanager_ensure_current_page_visible", "target": "webtoon_layout_manager_webtoonlayoutmanager_scroll_to_page", "relation": "calls", "confidence": "EXTRACTED", "source_file": "app\\ui\\canvas\\webtoons\\webtoon_layout_manager.py", "source_location": "L272", "weight": 1.0}, {"source": "webtoon_layout_manager_webtoonlayoutmanager_scene_to_page_coordinates", "target": "webtoon_layout_manager_webtoonlayoutmanager_get_page_at_position", "relation": "calls", "confidence": "EXTRACTED", "source_file": "app\\ui\\canvas\\webtoons\\webtoon_layout_manager.py", "source_location": "L302", "weight": 1.0}, {"source": "webtoon_layout_manager_webtoonlayoutmanager_recalculate_layout", "target": "webtoon_layout_manager_webtoonlayoutmanager_clear", "relation": "calls", "confidence": "EXTRACTED", "source_file": "app\\ui\\canvas\\webtoons\\webtoon_layout_manager.py", "source_location": "L336", "weight": 1.0}, {"source": "webtoon_layout_manager_rationale_1", "target": "app_ui_canvas_webtoons_webtoon_layout_manager_py", "relation": "rationale_for", "confidence": "EXTRACTED", "source_file": "app\\ui\\canvas\\webtoons\\webtoon_layout_manager.py", "source_location": "L1", "weight": 1.0}, {"source": "webtoon_layout_manager_rationale_13", "target": "webtoon_layout_manager_webtoonlayoutmanager", "relation": "rationale_for", "confidence": "EXTRACTED", "source_file": "app\\ui\\canvas\\webtoons\\webtoon_layout_manager.py", "source_location": "L13", "weight": 1.0}, {"source": "webtoon_layout_manager_rationale_46", "target": "webtoon_layout_manager_webtoonlayoutmanager_estimate_layout", "relation": "rationale_for", "confidence": "EXTRACTED", "source_file": "app\\ui\\canvas\\webtoons\\webtoon_layout_manager.py", "source_location": "L46", "weight": 1.0}, {"source": "webtoon_layout_manager_rationale_95", "target": "webtoon_layout_manager_webtoonlayoutmanager_adjust_layout_for_actual_size", "relation": "rationale_for", "confidence": "EXTRACTED", "source_file": "app\\ui\\canvas\\webtoons\\webtoon_layout_manager.py", "source_location": "L95", "weight": 1.0}, {"source": "webtoon_layout_manager_rationale_119", "target": "webtoon_layout_manager_webtoonlayoutmanager_get_visible_pages", "relation": "rationale_for", "confidence": "EXTRACTED", "source_file": "app\\ui\\canvas\\webtoons\\webtoon_layout_manager.py", "source_location": "L119", "weight": 1.0}, {"source": "webtoon_layout_manager_rationale_140", "target": "webtoon_layout_manager_webtoonlayoutmanager_get_pages_for_scene_bounds", "relation": "rationale_for", "confidence": "EXTRACTED", "source_file": "app\\ui\\canvas\\webtoons\\webtoon_layout_manager.py", "source_location": "L140", "weight": 1.0}, {"source": "webtoon_layout_manager_rationale_155", "target": "webtoon_layout_manager_webtoonlayoutmanager_get_page_at_position", "relation": "rationale_for", "confidence": "EXTRACTED", "source_file": "app\\ui\\canvas\\webtoons\\webtoon_layout_manager.py", "source_location": "L155", "weight": 1.0}, {"source": "webtoon_layout_manager_rationale_162", "target": "webtoon_layout_manager_webtoonlayoutmanager_scroll_to_page", "relation": "rationale_for", "confidence": "EXTRACTED", "source_file": "app\\ui\\canvas\\webtoons\\webtoon_layout_manager.py", "source_location": "L162", "weight": 1.0}, {"source": "webtoon_layout_manager_rationale_201", "target": "webtoon_layout_manager_webtoonlayoutmanager_update_current_page", "relation": "rationale_for", "confidence": "EXTRACTED", "source_file": "app\\ui\\canvas\\webtoons\\webtoon_layout_manager.py", "source_location": "L201", "weight": 1.0}, {"source": "webtoon_layout_manager_rationale_246", "target": "webtoon_layout_manager_webtoonlayoutmanager_update_page_on_click", "relation": "rationale_for", "confidence": "EXTRACTED", "source_file": "app\\ui\\canvas\\webtoons\\webtoon_layout_manager.py", "source_location": "L246", "weight": 1.0}, {"source": "webtoon_layout_manager_rationale_254", "target": "webtoon_layout_manager_webtoonlayoutmanager_ensure_current_page_visible", "relation": "rationale_for", "confidence": "EXTRACTED", "source_file": "app\\ui\\canvas\\webtoons\\webtoon_layout_manager.py", "source_location": "L254", "weight": 1.0}, {"source": "webtoon_layout_manager_rationale_275", "target": "webtoon_layout_manager_webtoonlayoutmanager_enable_page_detection_after_delay", "relation": "rationale_for", "confidence": "EXTRACTED", "source_file": "app\\ui\\canvas\\webtoons\\webtoon_layout_manager.py", "source_location": "L275", "weight": 1.0}, {"source": "webtoon_layout_manager_rationale_279", "target": "webtoon_layout_manager_webtoonlayoutmanager_enable_page_detection", "relation": "rationale_for", "confidence": "EXTRACTED", "source_file": "app\\ui\\canvas\\webtoons\\webtoon_layout_manager.py", "source_location": "L279", "weight": 1.0}, {"source": "webtoon_layout_manager_rationale_287", "target": "webtoon_layout_manager_webtoonlayoutmanager_set_page_detection_delay", "relation": "rationale_for", "confidence": "EXTRACTED", "source_file": "app\\ui\\canvas\\webtoons\\webtoon_layout_manager.py", "source_location": "L287", "weight": 1.0}, {"source": "webtoon_layout_manager_rationale_292", "target": "webtoon_layout_manager_webtoonlayoutmanager_get_page_detection_delay", "relation": "rationale_for", "confidence": "EXTRACTED", "source_file": "app\\ui\\canvas\\webtoons\\webtoon_layout_manager.py", "source_location": "L292", "weight": 1.0}, {"source": "webtoon_layout_manager_rationale_296", "target": "webtoon_layout_manager_webtoonlayoutmanager_disable_page_detection", "relation": "rationale_for", "confidence": "EXTRACTED", "source_file": "app\\ui\\canvas\\webtoons\\webtoon_layout_manager.py", "source_location": "L296", "weight": 1.0}, {"source": "webtoon_layout_manager_rationale_301", "target": "webtoon_layout_manager_webtoonlayoutmanager_scene_to_page_coordinates", "relation": "rationale_for", "confidence": "EXTRACTED", "source_file": "app\\ui\\canvas\\webtoons\\webtoon_layout_manager.py", "source_location": "L301", "weight": 1.0}, {"source": "webtoon_layout_manager_rationale_312", "target": "webtoon_layout_manager_webtoonlayoutmanager_page_to_scene_coordinates", "relation": "rationale_for", "confidence": "EXTRACTED", "source_file": "app\\ui\\canvas\\webtoons\\webtoon_layout_manager.py", "source_location": "L312", "weight": 1.0}, {"source": "webtoon_layout_manager_rationale_323", "target": "webtoon_layout_manager_webtoonlayoutmanager_clear", "relation": "rationale_for", "confidence": "EXTRACTED", "source_file": "app\\ui\\canvas\\webtoons\\webtoon_layout_manager.py", "source_location": "L323", "weight": 1.0}, {"source": "webtoon_layout_manager_rationale_333", "target": "webtoon_layout_manager_webtoonlayoutmanager_recalculate_layout", "relation": "rationale_for", "confidence": "EXTRACTED", "source_file": "app\\ui\\canvas\\webtoons\\webtoon_layout_manager.py", "source_location": "L333", "weight": 1.0}], "raw_calls": [{"caller_nid": "webtoon_layout_manager_webtoonlayoutmanager_init", "callee": "QTimer", "source_file": "app\\ui\\canvas\\webtoons\\webtoon_layout_manager.py", "source_location": "L35"}, {"caller_nid": "webtoon_layout_manager_webtoonlayoutmanager_init", "callee": "setSingleShot", "source_file": "app\\ui\\canvas\\webtoons\\webtoon_layout_manager.py", "source_location": "L36"}, {"caller_nid": "webtoon_layout_manager_webtoonlayoutmanager_init", "callee": "connect", "source_file": "app\\ui\\canvas\\webtoons\\webtoon_layout_manager.py", "source_location": "L37"}, {"caller_nid": "webtoon_layout_manager_webtoonlayoutmanager_estimate_layout", "callee": "min", "source_file": "app\\ui\\canvas\\webtoons\\webtoon_layout_manager.py", "source_location": "L49"}, {"caller_nid": "webtoon_layout_manager_webtoonlayoutmanager_estimate_layout", "callee": "len", "source_file": "app\\ui\\canvas\\webtoons\\webtoon_layout_manager.py", "source_location": "L49"}, {"caller_nid": "webtoon_layout_manager_webtoonlayoutmanager_estimate_layout", "callee": "range", "source_file": "app\\ui\\canvas\\webtoons\\webtoon_layout_manager.py", "source_location": "L53"}, {"caller_nid": "webtoon_layout_manager_webtoonlayoutmanager_estimate_layout", "callee": "read_image", "source_file": "app\\ui\\canvas\\webtoons\\webtoon_layout_manager.py", "source_location": "L57"}, {"caller_nid": "webtoon_layout_manager_webtoonlayoutmanager_estimate_layout", "callee": "append", "source_file": "app\\ui\\canvas\\webtoons\\webtoon_layout_manager.py", "source_location": "L60"}, {"caller_nid": "webtoon_layout_manager_webtoonlayoutmanager_estimate_layout", "callee": "append", "source_file": "app\\ui\\canvas\\webtoons\\webtoon_layout_manager.py", "source_location": "L61"}, {"caller_nid": "webtoon_layout_manager_webtoonlayoutmanager_estimate_layout", "callee": "append", "source_file": "app\\ui\\canvas\\webtoons\\webtoon_layout_manager.py", "source_location": "L64"}, {"caller_nid": "webtoon_layout_manager_webtoonlayoutmanager_estimate_layout", "callee": "append", "source_file": "app\\ui\\canvas\\webtoons\\webtoon_layout_manager.py", "source_location": "L65"}, {"caller_nid": "webtoon_layout_manager_webtoonlayoutmanager_estimate_layout", "callee": "sum", "source_file": "app\\ui\\canvas\\webtoons\\webtoon_layout_manager.py", "source_location": "L68"}, {"caller_nid": "webtoon_layout_manager_webtoonlayoutmanager_estimate_layout", "callee": "len", "source_file": "app\\ui\\canvas\\webtoons\\webtoon_layout_manager.py", "source_location": "L68"}, {"caller_nid": "webtoon_layout_manager_webtoonlayoutmanager_estimate_layout", "callee": "sum", "source_file": "app\\ui\\canvas\\webtoons\\webtoon_layout_manager.py", "source_location": "L69"}, {"caller_nid": "webtoon_layout_manager_webtoonlayoutmanager_estimate_layout", "callee": "len", "source_file": "app\\ui\\canvas\\webtoons\\webtoon_layout_manager.py", "source_location": "L69"}, {"caller_nid": "webtoon_layout_manager_webtoonlayoutmanager_estimate_layout", "callee": "range", "source_file": "app\\ui\\canvas\\webtoons\\webtoon_layout_manager.py", "source_location": "L78"}, {"caller_nid": "webtoon_layout_manager_webtoonlayoutmanager_estimate_layout", "callee": "len", "source_file": "app\\ui\\canvas\\webtoons\\webtoon_layout_manager.py", "source_location": "L78"}, {"caller_nid": "webtoon_layout_manager_webtoonlayoutmanager_estimate_layout", "callee": "append", "source_file": "app\\ui\\canvas\\webtoons\\webtoon_layout_manager.py", "source_location": "L79"}, {"caller_nid": "webtoon_layout_manager_webtoonlayoutmanager_estimate_layout", "callee": "min", "source_file": "app\\ui\\canvas\\webtoons\\webtoon_layout_manager.py", "source_location": "L81"}, {"caller_nid": "webtoon_layout_manager_webtoonlayoutmanager_estimate_layout", "callee": "len", "source_file": "app\\ui\\canvas\\webtoons\\webtoon_layout_manager.py", "source_location": "L81"}, {"caller_nid": "webtoon_layout_manager_webtoonlayoutmanager_estimate_layout", "callee": "append", "source_file": "app\\ui\\canvas\\webtoons\\webtoon_layout_manager.py", "source_location": "L82"}, {"caller_nid": "webtoon_layout_manager_webtoonlayoutmanager_estimate_layout", "callee": "setSceneRect", "source_file": "app\\ui\\canvas\\webtoons\\webtoon_layout_manager.py", "source_location": "L86"}, {"caller_nid": "webtoon_layout_manager_webtoonlayoutmanager_estimate_layout", "callee": "print", "source_file": "app\\ui\\canvas\\webtoons\\webtoon_layout_manager.py", "source_location": "L91"}, {"caller_nid": "webtoon_layout_manager_webtoonlayoutmanager_adjust_layout_for_actual_size", "callee": "len", "source_file": "app\\ui\\canvas\\webtoons\\webtoon_layout_manager.py", "source_location": "L96"}, {"caller_nid": "webtoon_layout_manager_webtoonlayoutmanager_adjust_layout_for_actual_size", "callee": "range", "source_file": "app\\ui\\canvas\\webtoons\\webtoon_layout_manager.py", "source_location": "L107"}, {"caller_nid": "webtoon_layout_manager_webtoonlayoutmanager_adjust_layout_for_actual_size", "callee": "len", "source_file": "app\\ui\\canvas\\webtoons\\webtoon_layout_manager.py", "source_location": "L107"}, {"caller_nid": "webtoon_layout_manager_webtoonlayoutmanager_adjust_layout_for_actual_size", "callee": "setSceneRect", "source_file": "app\\ui\\canvas\\webtoons\\webtoon_layout_manager.py", "source_location": "L112"}, {"caller_nid": "webtoon_layout_manager_webtoonlayoutmanager_get_visible_pages", "callee": "hasattr", "source_file": "app\\ui\\canvas\\webtoons\\webtoon_layout_manager.py", "source_location": "L121"}, {"caller_nid": "webtoon_layout_manager_webtoonlayoutmanager_get_visible_pages", "callee": "viewport", "source_file": "app\\ui\\canvas\\webtoons\\webtoon_layout_manager.py", "source_location": "L121"}, {"caller_nid": "webtoon_layout_manager_webtoonlayoutmanager_get_visible_pages", "callee": "boundingRect", "source_file": "app\\ui\\canvas\\webtoons\\webtoon_layout_manager.py", "source_location": "L122"}, {"caller_nid": "webtoon_layout_manager_webtoonlayoutmanager_get_visible_pages", "callee": "mapToScene", "source_file": "app\\ui\\canvas\\webtoons\\webtoon_layout_manager.py", "source_location": "L122"}, {"caller_nid": "webtoon_layout_manager_webtoonlayoutmanager_get_visible_pages", "callee": "rect", "source_file": "app\\ui\\canvas\\webtoons\\webtoon_layout_manager.py", "source_location": "L122"}, {"caller_nid": "webtoon_layout_manager_webtoonlayoutmanager_get_visible_pages", "callee": "viewport", "source_file": "app\\ui\\canvas\\webtoons\\webtoon_layout_manager.py", "source_location": "L122"}, {"caller_nid": "webtoon_layout_manager_webtoonlayoutmanager_get_visible_pages", "callee": "top", "source_file": "app\\ui\\canvas\\webtoons\\webtoon_layout_manager.py", "source_location": "L123"}, {"caller_nid": "webtoon_layout_manager_webtoonlayoutmanager_get_visible_pages", "callee": "bottom", "source_file": "app\\ui\\canvas\\webtoons\\webtoon_layout_manager.py", "source_location": "L124"}, {"caller_nid": "webtoon_layout_manager_webtoonlayoutmanager_get_visible_pages", "callee": "len", "source_file": "app\\ui\\canvas\\webtoons\\webtoon_layout_manager.py", "source_location": "L127"}, {"caller_nid": "webtoon_layout_manager_webtoonlayoutmanager_get_visible_pages", "callee": "set", "source_file": "app\\ui\\canvas\\webtoons\\webtoon_layout_manager.py", "source_location": "L131"}, {"caller_nid": "webtoon_layout_manager_webtoonlayoutmanager_get_visible_pages", "callee": "enumerate", "source_file": "app\\ui\\canvas\\webtoons\\webtoon_layout_manager.py", "source_location": "L132"}, {"caller_nid": "webtoon_layout_manager_webtoonlayoutmanager_get_visible_pages", "callee": "zip", "source_file": "app\\ui\\canvas\\webtoons\\webtoon_layout_manager.py", "source_location": "L132"}, {"caller_nid": "webtoon_layout_manager_webtoonlayoutmanager_get_visible_pages", "callee": "add", "source_file": "app\\ui\\canvas\\webtoons\\webtoon_layout_manager.py", "source_location": "L135"}, {"caller_nid": "webtoon_layout_manager_webtoonlayoutmanager_get_pages_for_scene_bounds", "callee": "set", "source_file": "app\\ui\\canvas\\webtoons\\webtoon_layout_manager.py", "source_location": "L141"}, {"caller_nid": "webtoon_layout_manager_webtoonlayoutmanager_get_pages_for_scene_bounds", "callee": "top", "source_file": "app\\ui\\canvas\\webtoons\\webtoon_layout_manager.py", "source_location": "L142"}, {"caller_nid": "webtoon_layout_manager_webtoonlayoutmanager_get_pages_for_scene_bounds", "callee": "bottom", "source_file": "app\\ui\\canvas\\webtoons\\webtoon_layout_manager.py", "source_location": "L143"}, {"caller_nid": "webtoon_layout_manager_webtoonlayoutmanager_get_pages_for_scene_bounds", "callee": "enumerate", "source_file": "app\\ui\\canvas\\webtoons\\webtoon_layout_manager.py", "source_location": "L145"}, {"caller_nid": "webtoon_layout_manager_webtoonlayoutmanager_get_pages_for_scene_bounds", "callee": "zip", "source_file": "app\\ui\\canvas\\webtoons\\webtoon_layout_manager.py", "source_location": "L145"}, {"caller_nid": "webtoon_layout_manager_webtoonlayoutmanager_get_pages_for_scene_bounds", "callee": "add", "source_file": "app\\ui\\canvas\\webtoons\\webtoon_layout_manager.py", "source_location": "L150"}, {"caller_nid": "webtoon_layout_manager_webtoonlayoutmanager_get_page_at_position", "callee": "enumerate", "source_file": "app\\ui\\canvas\\webtoons\\webtoon_layout_manager.py", "source_location": "L156"}, {"caller_nid": "webtoon_layout_manager_webtoonlayoutmanager_get_page_at_position", "callee": "zip", "source_file": "app\\ui\\canvas\\webtoons\\webtoon_layout_manager.py", "source_location": "L156"}, {"caller_nid": "webtoon_layout_manager_webtoonlayoutmanager_scroll_to_page", "callee": "len", "source_file": "app\\ui\\canvas\\webtoons\\webtoon_layout_manager.py", "source_location": "L163"}, {"caller_nid": "webtoon_layout_manager_webtoonlayoutmanager_scroll_to_page", "callee": "print", "source_file": "app\\ui\\canvas\\webtoons\\webtoon_layout_manager.py", "source_location": "L164"}, {"caller_nid": "webtoon_layout_manager_webtoonlayoutmanager_scroll_to_page", "callee": "len", "source_file": "app\\ui\\canvas\\webtoons\\webtoon_layout_manager.py", "source_location": "L164"}, {"caller_nid": "webtoon_layout_manager_webtoonlayoutmanager_scroll_to_page", "callee": "print", "source_file": "app\\ui\\canvas\\webtoons\\webtoon_layout_manager.py", "source_location": "L177"}, {"caller_nid": "webtoon_layout_manager_webtoonlayoutmanager_scroll_to_page", "callee": "print", "source_file": "app\\ui\\canvas\\webtoons\\webtoon_layout_manager.py", "source_location": "L178"}, {"caller_nid": "webtoon_layout_manager_webtoonlayoutmanager_scroll_to_page", "callee": "centerOn", "source_file": "app\\ui\\canvas\\webtoons\\webtoon_layout_manager.py", "source_location": "L185"}, {"caller_nid": "webtoon_layout_manager_webtoonlayoutmanager_scroll_to_page", "callee": "mapToScene", "source_file": "app\\ui\\canvas\\webtoons\\webtoon_layout_manager.py", "source_location": "L188"}, {"caller_nid": "webtoon_layout_manager_webtoonlayoutmanager_scroll_to_page", "callee": "center", "source_file": "app\\ui\\canvas\\webtoons\\webtoon_layout_manager.py", "source_location": "L188"}, {"caller_nid": "webtoon_layout_manager_webtoonlayoutmanager_scroll_to_page", "callee": "rect", "source_file": "app\\ui\\canvas\\webtoons\\webtoon_layout_manager.py", "source_location": "L188"}, {"caller_nid": "webtoon_layout_manager_webtoonlayoutmanager_scroll_to_page", "callee": "viewport", "source_file": "app\\ui\\canvas\\webtoons\\webtoon_layout_manager.py", "source_location": "L188"}, {"caller_nid": "webtoon_layout_manager_webtoonlayoutmanager_scroll_to_page", "callee": "print", "source_file": "app\\ui\\canvas\\webtoons\\webtoon_layout_manager.py", "source_location": "L189"}, {"caller_nid": "webtoon_layout_manager_webtoonlayoutmanager_scroll_to_page", "callee": "x", "source_file": "app\\ui\\canvas\\webtoons\\webtoon_layout_manager.py", "source_location": "L189"}, {"caller_nid": "webtoon_layout_manager_webtoonlayoutmanager_scroll_to_page", "callee": "y", "source_file": "app\\ui\\canvas\\webtoons\\webtoon_layout_manager.py", "source_location": "L189"}, {"caller_nid": "webtoon_layout_manager_webtoonlayoutmanager_scroll_to_page", "callee": "_enable_page_detection_after_delay", "source_file": "app\\ui\\canvas\\webtoons\\webtoon_layout_manager.py", "source_location": "L192"}, {"caller_nid": "webtoon_layout_manager_webtoonlayoutmanager_scroll_to_page", "callee": "emit", "source_file": "app\\ui\\canvas\\webtoons\\webtoon_layout_manager.py", "source_location": "L196"}, {"caller_nid": "webtoon_layout_manager_webtoonlayoutmanager_update_current_page", "callee": "y", "source_file": "app\\ui\\canvas\\webtoons\\webtoon_layout_manager.py", "source_location": "L206"}, {"caller_nid": "webtoon_layout_manager_webtoonlayoutmanager_update_current_page", "callee": "mapToScene", "source_file": "app\\ui\\canvas\\webtoons\\webtoon_layout_manager.py", "source_location": "L206"}, {"caller_nid": "webtoon_layout_manager_webtoonlayoutmanager_update_current_page", "callee": "center", "source_file": "app\\ui\\canvas\\webtoons\\webtoon_layout_manager.py", "source_location": "L206"}, {"caller_nid": "webtoon_layout_manager_webtoonlayoutmanager_update_current_page", "callee": "rect", "source_file": "app\\ui\\canvas\\webtoons\\webtoon_layout_manager.py", "source_location": "L206"}, {"caller_nid": "webtoon_layout_manager_webtoonlayoutmanager_update_current_page", "callee": "viewport", "source_file": "app\\ui\\canvas\\webtoons\\webtoon_layout_manager.py", "source_location": "L206"}, {"caller_nid": "webtoon_layout_manager_webtoonlayoutmanager_update_current_page", "callee": "float", "source_file": "app\\ui\\canvas\\webtoons\\webtoon_layout_manager.py", "source_location": "L212"}, {"caller_nid": "webtoon_layout_manager_webtoonlayoutmanager_update_current_page", "callee": "enumerate", "source_file": "app\\ui\\canvas\\webtoons\\webtoon_layout_manager.py", "source_location": "L214"}, {"caller_nid": "webtoon_layout_manager_webtoonlayoutmanager_update_current_page", "callee": "zip", "source_file": "app\\ui\\canvas\\webtoons\\webtoon_layout_manager.py", "source_location": "L214"}, {"caller_nid": "webtoon_layout_manager_webtoonlayoutmanager_update_current_page", "callee": "abs", "source_file": "app\\ui\\canvas\\webtoons\\webtoon_layout_manager.py", "source_location": "L233"}, {"caller_nid": "webtoon_layout_manager_webtoonlayoutmanager_update_page_on_click", "callee": "y", "source_file": "app\\ui\\canvas\\webtoons\\webtoon_layout_manager.py", "source_location": "L247"}, {"caller_nid": "webtoon_layout_manager_webtoonlayoutmanager_ensure_current_page_visible", "callee": "print", "source_file": "app\\ui\\canvas\\webtoons\\webtoon_layout_manager.py", "source_location": "L255"}, {"caller_nid": "webtoon_layout_manager_webtoonlayoutmanager_ensure_current_page_visible", "callee": "fitInView", "source_file": "app\\ui\\canvas\\webtoons\\webtoon_layout_manager.py", "source_location": "L258"}, {"caller_nid": "webtoon_layout_manager_webtoonlayoutmanager_ensure_current_page_visible", "callee": "y", "source_file": "app\\ui\\canvas\\webtoons\\webtoon_layout_manager.py", "source_location": "L261"}, {"caller_nid": "webtoon_layout_manager_webtoonlayoutmanager_ensure_current_page_visible", "callee": "mapToScene", "source_file": "app\\ui\\canvas\\webtoons\\webtoon_layout_manager.py", "source_location": "L261"}, {"caller_nid": "webtoon_layout_manager_webtoonlayoutmanager_ensure_current_page_visible", "callee": "center", "source_file": "app\\ui\\canvas\\webtoons\\webtoon_layout_manager.py", "source_location": "L261"}, {"caller_nid": "webtoon_layout_manager_webtoonlayoutmanager_ensure_current_page_visible", "callee": "rect", "source_file": "app\\ui\\canvas\\webtoons\\webtoon_layout_manager.py", "source_location": "L261"}, {"caller_nid": "webtoon_layout_manager_webtoonlayoutmanager_ensure_current_page_visible", "callee": "viewport", "source_file": "app\\ui\\canvas\\webtoons\\webtoon_layout_manager.py", "source_location": "L261"}, {"caller_nid": "webtoon_layout_manager_webtoonlayoutmanager_ensure_current_page_visible", "callee": "print", "source_file": "app\\ui\\canvas\\webtoons\\webtoon_layout_manager.py", "source_location": "L264"}, {"caller_nid": "webtoon_layout_manager_webtoonlayoutmanager_ensure_current_page_visible", "callee": "abs", "source_file": "app\\ui\\canvas\\webtoons\\webtoon_layout_manager.py", "source_location": "L267"}, {"caller_nid": "webtoon_layout_manager_webtoonlayoutmanager_ensure_current_page_visible", "callee": "print", "source_file": "app\\ui\\canvas\\webtoons\\webtoon_layout_manager.py", "source_location": "L269"}, {"caller_nid": "webtoon_layout_manager_webtoonlayoutmanager_enable_page_detection_after_delay", "callee": "start", "source_file": "app\\ui\\canvas\\webtoons\\webtoon_layout_manager.py", "source_location": "L276"}, {"caller_nid": "webtoon_layout_manager_webtoonlayoutmanager_enable_page_detection", "callee": "on_page_detection_enabled", "source_file": "app\\ui\\canvas\\webtoons\\webtoon_layout_manager.py", "source_location": "L284"}, {"caller_nid": "webtoon_layout_manager_webtoonlayoutmanager_set_page_detection_delay", "callee": "setInterval", "source_file": "app\\ui\\canvas\\webtoons\\webtoon_layout_manager.py", "source_location": "L289"}, {"caller_nid": "webtoon_layout_manager_webtoonlayoutmanager_get_page_detection_delay", "callee": "interval", "source_file": "app\\ui\\canvas\\webtoons\\webtoon_layout_manager.py", "source_location": "L293"}, {"caller_nid": "webtoon_layout_manager_webtoonlayoutmanager_get_page_detection_delay", "callee": "hasattr", "source_file": "app\\ui\\canvas\\webtoons\\webtoon_layout_manager.py", "source_location": "L293"}, {"caller_nid": "webtoon_layout_manager_webtoonlayoutmanager_disable_page_detection", "callee": "stop", "source_file": "app\\ui\\canvas\\webtoons\\webtoon_layout_manager.py", "source_location": "L298"}, {"caller_nid": "webtoon_layout_manager_webtoonlayoutmanager_scene_to_page_coordinates", "callee": "y", "source_file": "app\\ui\\canvas\\webtoons\\webtoon_layout_manager.py", "source_location": "L302"}, {"caller_nid": "webtoon_layout_manager_webtoonlayoutmanager_scene_to_page_coordinates", "callee": "len", "source_file": "app\\ui\\canvas\\webtoons\\webtoon_layout_manager.py", "source_location": "L303"}, {"caller_nid": "webtoon_layout_manager_webtoonlayoutmanager_scene_to_page_coordinates", "callee": "x", "source_file": "app\\ui\\canvas\\webtoons\\webtoon_layout_manager.py", "source_location": "L306"}, {"caller_nid": "webtoon_layout_manager_webtoonlayoutmanager_scene_to_page_coordinates", "callee": "y", "source_file": "app\\ui\\canvas\\webtoons\\webtoon_layout_manager.py", "source_location": "L307"}, {"caller_nid": "webtoon_layout_manager_webtoonlayoutmanager_scene_to_page_coordinates", "callee": "QPointF", "source_file": "app\\ui\\canvas\\webtoons\\webtoon_layout_manager.py", "source_location": "L308"}, {"caller_nid": "webtoon_layout_manager_webtoonlayoutmanager_page_to_scene_coordinates", "callee": "len", "source_file": "app\\ui\\canvas\\webtoons\\webtoon_layout_manager.py", "source_location": "L313"}, {"caller_nid": "webtoon_layout_manager_webtoonlayoutmanager_page_to_scene_coordinates", "callee": "x", "source_file": "app\\ui\\canvas\\webtoons\\webtoon_layout_manager.py", "source_location": "L318"}, {"caller_nid": "webtoon_layout_manager_webtoonlayoutmanager_page_to_scene_coordinates", "callee": "y", "source_file": "app\\ui\\canvas\\webtoons\\webtoon_layout_manager.py", "source_location": "L319"}, {"caller_nid": "webtoon_layout_manager_webtoonlayoutmanager_page_to_scene_coordinates", "callee": "QPointF", "source_file": "app\\ui\\canvas\\webtoons\\webtoon_layout_manager.py", "source_location": "L320"}, {"caller_nid": "webtoon_layout_manager_webtoonlayoutmanager_clear", "callee": "stop", "source_file": "app\\ui\\canvas\\webtoons\\webtoon_layout_manager.py", "source_location": "L324"}, {"caller_nid": "webtoon_layout_manager_webtoonlayoutmanager_recalculate_layout", "callee": "setSceneRect", "source_file": "app\\ui\\canvas\\webtoons\\webtoon_layout_manager.py", "source_location": "L338"}, {"caller_nid": "webtoon_layout_manager_webtoonlayoutmanager_recalculate_layout", "callee": "range", "source_file": "app\\ui\\canvas\\webtoons\\webtoon_layout_manager.py", "source_location": "L345"}, {"caller_nid": "webtoon_layout_manager_webtoonlayoutmanager_recalculate_layout", "callee": "len", "source_file": "app\\ui\\canvas\\webtoons\\webtoon_layout_manager.py", "source_location": "L345"}, {"caller_nid": "webtoon_layout_manager_webtoonlayoutmanager_recalculate_layout", "callee": "append", "source_file": "app\\ui\\canvas\\webtoons\\webtoon_layout_manager.py", "source_location": "L346"}, {"caller_nid": "webtoon_layout_manager_webtoonlayoutmanager_recalculate_layout", "callee": "len", "source_file": "app\\ui\\canvas\\webtoons\\webtoon_layout_manager.py", "source_location": "L348"}, {"caller_nid": "webtoon_layout_manager_webtoonlayoutmanager_recalculate_layout", "callee": "QRectF", "source_file": "app\\ui\\canvas\\webtoons\\webtoon_layout_manager.py", "source_location": "L358"}, {"caller_nid": "webtoon_layout_manager_webtoonlayoutmanager_recalculate_layout", "callee": "setSceneRect", "source_file": "app\\ui\\canvas\\webtoons\\webtoon_layout_manager.py", "source_location": "L359"}, {"caller_nid": "webtoon_layout_manager_webtoonlayoutmanager_recalculate_layout", "callee": "setSceneRect", "source_file": "app\\ui\\canvas\\webtoons\\webtoon_layout_manager.py", "source_location": "L362"}, {"caller_nid": "webtoon_layout_manager_webtoonlayoutmanager_recalculate_layout", "callee": "list", "source_file": "app\\ui\\canvas\\webtoons\\webtoon_layout_manager.py", "source_location": "L365"}, {"caller_nid": "webtoon_layout_manager_webtoonlayoutmanager_recalculate_layout", "callee": "len", "source_file": "app\\ui\\canvas\\webtoons\\webtoon_layout_manager.py", "source_location": "L366"}, {"caller_nid": "webtoon_layout_manager_webtoonlayoutmanager_recalculate_layout", "callee": "x", "source_file": "app\\ui\\canvas\\webtoons\\webtoon_layout_manager.py", "source_location": "L374"}, {"caller_nid": "webtoon_layout_manager_webtoonlayoutmanager_recalculate_layout", "callee": "pos", "source_file": "app\\ui\\canvas\\webtoons\\webtoon_layout_manager.py", "source_location": "L374"}, {"caller_nid": "webtoon_layout_manager_webtoonlayoutmanager_recalculate_layout", "callee": "setPos", "source_file": "app\\ui\\canvas\\webtoons\\webtoon_layout_manager.py", "source_location": "L375"}, {"caller_nid": "webtoon_layout_manager_webtoonlayoutmanager_recalculate_layout", "callee": "list", "source_file": "app\\ui\\canvas\\webtoons\\webtoon_layout_manager.py", "source_location": "L378"}, {"caller_nid": "webtoon_layout_manager_webtoonlayoutmanager_recalculate_layout", "callee": "keys", "source_file": "app\\ui\\canvas\\webtoons\\webtoon_layout_manager.py", "source_location": "L378"}, {"caller_nid": "webtoon_layout_manager_webtoonlayoutmanager_recalculate_layout", "callee": "len", "source_file": "app\\ui\\canvas\\webtoons\\webtoon_layout_manager.py", "source_location": "L379"}, {"caller_nid": "webtoon_layout_manager_webtoonlayoutmanager_recalculate_layout", "callee": "setPos", "source_file": "app\\ui\\canvas\\webtoons\\webtoon_layout_manager.py", "source_location": "L382"}]}