{"nodes": [{"id": "app_controllers_search_replace_py", "label": "search_replace.py", "file_type": "code", "source_file": "app\\controllers\\search_replace.py", "source_location": "L1"}, {"id": "search_replace_searchreplacecontroller", "label": "SearchReplaceController", "file_type": "code", "source_file": "app\\controllers\\search_replace.py", "source_location": "L22"}, {"id": "searchreplaceapplymixin", "label": "SearchReplaceApplyMixin", "file_type": "code", "source_file": "", "source_location": ""}, {"id": "searchreplaceselectionmixin", "label": "SearchReplaceSelectionMixin", "file_type": "code", "source_file": "", "source_location": ""}, {"id": "searchreplacejumpmixin", "label": "SearchReplaceJumpMixin", "file_type": "code", "source_file": "", "source_location": ""}, {"id": "search_replace_searchreplacecontroller_init", "label": ".__init__()", "file_type": "code", "source_file": "app\\controllers\\search_replace.py", "source_location": "L28"}, {"id": "search_replace_searchreplacecontroller_focus_find", "label": ".focus_find()", "file_type": "code", "source_file": "app\\controllers\\search_replace.py", "source_location": "L62"}, {"id": "search_replace_searchreplacecontroller_focus_replace", "label": ".focus_replace()", "file_type": "code", "source_file": "app\\controllers\\search_replace.py", "source_location": "L70"}, {"id": "search_replace_searchreplacecontroller_capture_focus_state", "label": "._capture_focus_state()", "file_type": "code", "source_file": "app\\controllers\\search_replace.py", "source_location": "L78"}, {"id": "search_replace_searchreplacecontroller_restore_focus_state", "label": "._restore_focus_state()", "file_type": "code", "source_file": "app\\controllers\\search_replace.py", "source_location": "L100"}, {"id": "search_replace_searchreplacecontroller_gather_options", "label": "._gather_options()", "file_type": "code", "source_file": "app\\controllers\\search_replace.py", "source_location": "L131"}, {"id": "search_replace_searchreplacecontroller_format_pattern_error", "label": "._format_pattern_error()", "file_type": "code", "source_file": "app\\controllers\\search_replace.py", "source_location": "L144"}, {"id": "search_replace_searchreplacecontroller_on_undo_redo", "label": ".on_undo_redo()", "file_type": "code", "source_file": "app\\controllers\\search_replace.py", "source_location": "L153"}, {"id": "search_replace_searchreplacecontroller_iter_blocks", "label": "._iter_blocks()", "file_type": "code", "source_file": "app\\controllers\\search_replace.py", "source_location": "L162"}, {"id": "search_replace_searchreplacecontroller_search", "label": ".search()", "file_type": "code", "source_file": "app\\controllers\\search_replace.py", "source_location": "L229"}, {"id": "search_replace_searchreplacecontroller_next_match", "label": ".next_match()", "file_type": "code", "source_file": "app\\controllers\\search_replace.py", "source_location": "L303"}, {"id": "search_replace_searchreplacecontroller_prev_match", "label": ".prev_match()", "file_type": "code", "source_file": "app\\controllers\\search_replace.py", "source_location": "L314"}, {"id": "search_replace_rationale_145", "label": "Map common validation errors to localized strings.", "file_type": "rationale", "source_file": "app\\controllers\\search_replace.py", "source_location": "L145"}, {"id": "search_replace_rationale_154", "label": "Refresh search results after undo/redo without jumping/focusing.", "file_type": "rationale", "source_file": "app\\controllers\\search_replace.py", "source_location": "L154"}, {"id": "search_replace_rationale_163", "label": "Yields (file_path, blk_list, index, blk) for the requested scope.", "file_type": "rationale", "source_file": "app\\controllers\\search_replace.py", "source_location": "L163"}], "edges": [{"source": "app_controllers_search_replace_py", "target": "typing", "relation": "imports_from", "confidence": "EXTRACTED", "source_file": "app\\controllers\\search_replace.py", "source_location": "L3", "weight": 1.0}, {"source": "app_controllers_search_replace_py", "target": "pyside6", "relation": "imports_from", "confidence": "EXTRACTED", "source_file": "app\\controllers\\search_replace.py", "source_location": "L5", "weight": 1.0}, {"source": "app_controllers_search_replace_py", "target": "app_controllers_search_replace_apply_mixin", "relation": "imports_from", "confidence": "EXTRACTED", "source_file": "app\\controllers\\search_replace.py", "source_location": "L7", "weight": 1.0}, {"source": "app_controllers_search_replace_py", "target": "app_controllers_search_replace_core", "relation": "imports_from", "confidence": "EXTRACTED", "source_file": "app\\controllers\\search_replace.py", "source_location": "L8", "weight": 1.0}, {"source": "app_controllers_search_replace_py", "target": "app_controllers_search_replace_jump_mixin", "relation": "imports_from", "confidence": "EXTRACTED", "source_file": "app\\controllers\\search_replace.py", "source_location": "L16", "weight": 1.0}, {"source": "app_controllers_search_replace_py", "target": "app_controllers_search_replace_selection_mixin", "relation": "imports_from", "confidence": "EXTRACTED", "source_file": "app\\controllers\\search_replace.py", "source_location": "L17", "weight": 1.0}, {"source": "app_controllers_search_replace_py", "target": "controller", "relation": "imports_from", "confidence": "EXTRACTED", "source_file": "app\\controllers\\search_replace.py", "source_location": "L19", "weight": 1.0}, {"source": "app_controllers_search_replace_py", "target": "search_replace_searchreplacecontroller", "relation": "contains", "confidence": "EXTRACTED", "source_file": "app\\controllers\\search_replace.py", "source_location": "L22", "weight": 1.0}, {"source": "search_replace_searchreplacecontroller", "target": "searchreplaceapplymixin", "relation": "inherits", "confidence": "EXTRACTED", "source_file": "app\\controllers\\search_replace.py", "source_location": "L22", "weight": 1.0}, {"source": "search_replace_searchreplacecontroller", "target": "searchreplaceselectionmixin", "relation": "inherits", "confidence": "EXTRACTED", "source_file": "app\\controllers\\search_replace.py", "source_location": "L22", "weight": 1.0}, {"source": "search_replace_searchreplacecontroller", "target": "searchreplacejumpmixin", "relation": "inherits", "confidence": "EXTRACTED", "source_file": "app\\controllers\\search_replace.py", "source_location": "L22", "weight": 1.0}, {"source": "search_replace_searchreplacecontroller", "target": "search_replace_searchreplacecontroller_init", "relation": "method", "confidence": "EXTRACTED", "source_file": "app\\controllers\\search_replace.py", "source_location": "L28", "weight": 1.0}, {"source": "search_replace_searchreplacecontroller", "target": "search_replace_searchreplacecontroller_focus_find", "relation": "method", "confidence": "EXTRACTED", "source_file": "app\\controllers\\search_replace.py", "source_location": "L62", "weight": 1.0}, {"source": "search_replace_searchreplacecontroller", "target": "search_replace_searchreplacecontroller_focus_replace", "relation": "method", "confidence": "EXTRACTED", "source_file": "app\\controllers\\search_replace.py", "source_location": "L70", "weight": 1.0}, {"source": "search_replace_searchreplacecontroller", "target": "search_replace_searchreplacecontroller_capture_focus_state", "relation": "method", "confidence": "EXTRACTED", "source_file": "app\\controllers\\search_replace.py", "source_location": "L78", "weight": 1.0}, {"source": "search_replace_searchreplacecontroller", "target": "search_replace_searchreplacecontroller_restore_focus_state", "relation": "method", "confidence": "EXTRACTED", "source_file": "app\\controllers\\search_replace.py", "source_location": "L100", "weight": 1.0}, {"source": "search_replace_searchreplacecontroller", "target": "search_replace_searchreplacecontroller_gather_options", "relation": "method", "confidence": "EXTRACTED", "source_file": "app\\controllers\\search_replace.py", "source_location": "L131", "weight": 1.0}, {"source": "search_replace_searchreplacecontroller", "target": "search_replace_searchreplacecontroller_format_pattern_error", "relation": "method", "confidence": "EXTRACTED", "source_file": "app\\controllers\\search_replace.py", "source_location": "L144", "weight": 1.0}, {"source": "search_replace_searchreplacecontroller", "target": "search_replace_searchreplacecontroller_on_undo_redo", "relation": "method", "confidence": "EXTRACTED", "source_file": "app\\controllers\\search_replace.py", "source_location": "L153", "weight": 1.0}, {"source": "search_replace_searchreplacecontroller", "target": "search_replace_searchreplacecontroller_iter_blocks", "relation": "method", "confidence": "EXTRACTED", "source_file": "app\\controllers\\search_replace.py", "source_location": "L162", "weight": 1.0}, {"source": "search_replace_searchreplacecontroller", "target": "search_replace_searchreplacecontroller_search", "relation": "method", "confidence": "EXTRACTED", "source_file": "app\\controllers\\search_replace.py", "source_location": "L229", "weight": 1.0}, {"source": "search_replace_searchreplacecontroller", "target": "search_replace_searchreplacecontroller_next_match", "relation": "method", "confidence": "EXTRACTED", "source_file": "app\\controllers\\search_replace.py", "source_location": "L303", "weight": 1.0}, {"source": "search_replace_searchreplacecontroller", "target": "search_replace_searchreplacecontroller_prev_match", "relation": "method", "confidence": "EXTRACTED", "source_file": "app\\controllers\\search_replace.py", "source_location": "L314", "weight": 1.0}, {"source": "search_replace_searchreplacecontroller_on_undo_redo", "target": "search_replace_searchreplacecontroller_search", "relation": "calls", "confidence": "EXTRACTED", "source_file": "app\\controllers\\search_replace.py", "source_location": "L160", "weight": 1.0}, {"source": "search_replace_searchreplacecontroller_search", "target": "search_replace_searchreplacecontroller_gather_options", "relation": "calls", "confidence": "EXTRACTED", "source_file": "app\\controllers\\search_replace.py", "source_location": "L231", "weight": 1.0}, {"source": "search_replace_searchreplacecontroller_search", "target": "search_replace_searchreplacecontroller_capture_focus_state", "relation": "calls", "confidence": "EXTRACTED", "source_file": "app\\controllers\\search_replace.py", "source_location": "L232", "weight": 1.0}, {"source": "search_replace_searchreplacecontroller_search", "target": "search_replace_searchreplacecontroller_format_pattern_error", "relation": "calls", "confidence": "EXTRACTED", "source_file": "app\\controllers\\search_replace.py", "source_location": "L239", "weight": 1.0}, {"source": "search_replace_searchreplacecontroller_search", "target": "search_replace_searchreplacecontroller_iter_blocks", "relation": "calls", "confidence": "EXTRACTED", "source_file": "app\\controllers\\search_replace.py", "source_location": "L248", "weight": 1.0}, {"source": "search_replace_searchreplacecontroller_next_match", "target": "search_replace_searchreplacecontroller_capture_focus_state", "relation": "calls", "confidence": "EXTRACTED", "source_file": "app\\controllers\\search_replace.py", "source_location": "L308", "weight": 1.0}, {"source": "search_replace_searchreplacecontroller_prev_match", "target": "search_replace_searchreplacecontroller_capture_focus_state", "relation": "calls", "confidence": "EXTRACTED", "source_file": "app\\controllers\\search_replace.py", "source_location": "L319", "weight": 1.0}, {"source": "search_replace_rationale_145", "target": "search_replace_searchreplacecontroller_format_pattern_error", "relation": "rationale_for", "confidence": "EXTRACTED", "source_file": "app\\controllers\\search_replace.py", "source_location": "L145", "weight": 1.0}, {"source": "search_replace_rationale_154", "target": "search_replace_searchreplacecontroller_on_undo_redo", "relation": "rationale_for", "confidence": "EXTRACTED", "source_file": "app\\controllers\\search_replace.py", "source_location": "L154", "weight": 1.0}, {"source": "search_replace_rationale_163", "target": "search_replace_searchreplacecontroller_iter_blocks", "relation": "rationale_for", "confidence": "EXTRACTED", "source_file": "app\\controllers\\search_replace.py", "source_location": "L163", "weight": 1.0}], "raw_calls": [{"caller_nid": "search_replace_searchreplacecontroller_init", "callee": "super", "source_file": "app\\controllers\\search_replace.py", "source_location": "L29"}, {"caller_nid": "search_replace_searchreplacecontroller_init", "callee": "getattr", "source_file": "app\\controllers\\search_replace.py", "source_location": "L36"}, {"caller_nid": "search_replace_searchreplacecontroller_init", "callee": "connect", "source_file": "app\\controllers\\search_replace.py", "source_location": "L40"}, {"caller_nid": "search_replace_searchreplacecontroller_init", "callee": "connect", "source_file": "app\\controllers\\search_replace.py", "source_location": "L41"}, {"caller_nid": "search_replace_searchreplacecontroller_init", "callee": "connect", "source_file": "app\\controllers\\search_replace.py", "source_location": "L42"}, {"caller_nid": "search_replace_searchreplacecontroller_init", "callee": "connect", "source_file": "app\\controllers\\search_replace.py", "source_location": "L43"}, {"caller_nid": "search_replace_searchreplacecontroller_init", "callee": "connect", "source_file": "app\\controllers\\search_replace.py", "source_location": "L44"}, {"caller_nid": "search_replace_searchreplacecontroller_init", "callee": "connect", "source_file": "app\\controllers\\search_replace.py", "source_location": "L45"}, {"caller_nid": "search_replace_searchreplacecontroller_init", "callee": "QShortcut", "source_file": "app\\controllers\\search_replace.py", "source_location": "L48"}, {"caller_nid": "search_replace_searchreplacecontroller_init", "callee": "QShortcut", "source_file": "app\\controllers\\search_replace.py", "source_location": "L49"}, {"caller_nid": "search_replace_searchreplacecontroller_init", "callee": "connect", "source_file": "app\\controllers\\search_replace.py", "source_location": "L52"}, {"caller_nid": "search_replace_searchreplacecontroller_init", "callee": "append", "source_file": "app\\controllers\\search_replace.py", "source_location": "L53"}, {"caller_nid": "search_replace_searchreplacecontroller_init", "callee": "QShortcut", "source_file": "app\\controllers\\search_replace.py", "source_location": "L54"}, {"caller_nid": "search_replace_searchreplacecontroller_init", "callee": "QKeySequence", "source_file": "app\\controllers\\search_replace.py", "source_location": "L54"}, {"caller_nid": "search_replace_searchreplacecontroller_init", "callee": "QShortcut", "source_file": "app\\controllers\\search_replace.py", "source_location": "L58"}, {"caller_nid": "search_replace_searchreplacecontroller_init", "callee": "QKeySequence", "source_file": "app\\controllers\\search_replace.py", "source_location": "L58"}, {"caller_nid": "search_replace_searchreplacecontroller_init", "callee": "setContext", "source_file": "app\\controllers\\search_replace.py", "source_location": "L59"}, {"caller_nid": "search_replace_searchreplacecontroller_init", "callee": "append", "source_file": "app\\controllers\\search_replace.py", "source_location": "L60"}, {"caller_nid": "search_replace_searchreplacecontroller_focus_find", "callee": "hasattr", "source_file": "app\\controllers\\search_replace.py", "source_location": "L63"}, {"caller_nid": "search_replace_searchreplacecontroller_focus_find", "callee": "show_search_sidebar", "source_file": "app\\controllers\\search_replace.py", "source_location": "L64"}, {"caller_nid": "search_replace_searchreplacecontroller_focus_find", "callee": "setFocus", "source_file": "app\\controllers\\search_replace.py", "source_location": "L67"}, {"caller_nid": "search_replace_searchreplacecontroller_focus_find", "callee": "selectAll", "source_file": "app\\controllers\\search_replace.py", "source_location": "L68"}, {"caller_nid": "search_replace_searchreplacecontroller_focus_replace", "callee": "hasattr", "source_file": "app\\controllers\\search_replace.py", "source_location": "L71"}, {"caller_nid": "search_replace_searchreplacecontroller_focus_replace", "callee": "show_search_sidebar", "source_file": "app\\controllers\\search_replace.py", "source_location": "L72"}, {"caller_nid": "search_replace_searchreplacecontroller_focus_replace", "callee": "setFocus", "source_file": "app\\controllers\\search_replace.py", "source_location": "L75"}, {"caller_nid": "search_replace_searchreplacecontroller_focus_replace", "callee": "selectAll", "source_file": "app\\controllers\\search_replace.py", "source_location": "L76"}, {"caller_nid": "search_replace_searchreplacecontroller_capture_focus_state", "callee": "focusWidget", "source_file": "app\\controllers\\search_replace.py", "source_location": "L80"}, {"caller_nid": "search_replace_searchreplacecontroller_capture_focus_state", "callee": "hasattr", "source_file": "app\\controllers\\search_replace.py", "source_location": "L86"}, {"caller_nid": "search_replace_searchreplacecontroller_capture_focus_state", "callee": "hasattr", "source_file": "app\\controllers\\search_replace.py", "source_location": "L86"}, {"caller_nid": "search_replace_searchreplacecontroller_capture_focus_state", "callee": "hasattr", "source_file": "app\\controllers\\search_replace.py", "source_location": "L86"}, {"caller_nid": "search_replace_searchreplacecontroller_capture_focus_state", "callee": "int", "source_file": "app\\controllers\\search_replace.py", "source_location": "L88"}, {"caller_nid": "search_replace_searchreplacecontroller_capture_focus_state", "callee": "selectionStart", "source_file": "app\\controllers\\search_replace.py", "source_location": "L88"}, {"caller_nid": "search_replace_searchreplacecontroller_capture_focus_state", "callee": "len", "source_file": "app\\controllers\\search_replace.py", "source_location": "L89"}, {"caller_nid": "search_replace_searchreplacecontroller_capture_focus_state", "callee": "selectedText", "source_file": "app\\controllers\\search_replace.py", "source_location": "L89"}, {"caller_nid": "search_replace_searchreplacecontroller_capture_focus_state", "callee": "int", "source_file": "app\\controllers\\search_replace.py", "source_location": "L92"}, {"caller_nid": "search_replace_searchreplacecontroller_capture_focus_state", "callee": "cursorPosition", "source_file": "app\\controllers\\search_replace.py", "source_location": "L92"}, {"caller_nid": "search_replace_searchreplacecontroller_restore_focus_state", "callee": "get", "source_file": "app\\controllers\\search_replace.py", "source_location": "L103"}, {"caller_nid": "search_replace_searchreplacecontroller_restore_focus_state", "callee": "isVisible", "source_file": "app\\controllers\\search_replace.py", "source_location": "L107"}, {"caller_nid": "search_replace_searchreplacecontroller_restore_focus_state", "callee": "singleShot", "source_file": "app\\controllers\\search_replace.py", "source_location": "L129"}, {"caller_nid": "search_replace_searchreplacecontroller_gather_options", "callee": "SearchOptions", "source_file": "app\\controllers\\search_replace.py", "source_location": "L133"}, {"caller_nid": "search_replace_searchreplacecontroller_gather_options", "callee": "text", "source_file": "app\\controllers\\search_replace.py", "source_location": "L134"}, {"caller_nid": "search_replace_searchreplacecontroller_gather_options", "callee": "text", "source_file": "app\\controllers\\search_replace.py", "source_location": "L135"}, {"caller_nid": "search_replace_searchreplacecontroller_gather_options", "callee": "isChecked", "source_file": "app\\controllers\\search_replace.py", "source_location": "L136"}, {"caller_nid": "search_replace_searchreplacecontroller_gather_options", "callee": "isChecked", "source_file": "app\\controllers\\search_replace.py", "source_location": "L137"}, {"caller_nid": "search_replace_searchreplacecontroller_gather_options", "callee": "isChecked", "source_file": "app\\controllers\\search_replace.py", "source_location": "L138"}, {"caller_nid": "search_replace_searchreplacecontroller_gather_options", "callee": "isChecked", "source_file": "app\\controllers\\search_replace.py", "source_location": "L139"}, {"caller_nid": "search_replace_searchreplacecontroller_gather_options", "callee": "currentData", "source_file": "app\\controllers\\search_replace.py", "source_location": "L140"}, {"caller_nid": "search_replace_searchreplacecontroller_gather_options", "callee": "currentData", "source_file": "app\\controllers\\search_replace.py", "source_location": "L141"}, {"caller_nid": "search_replace_searchreplacecontroller_format_pattern_error", "callee": "str", "source_file": "app\\controllers\\search_replace.py", "source_location": "L148"}, {"caller_nid": "search_replace_searchreplacecontroller_format_pattern_error", "callee": "isinstance", "source_file": "app\\controllers\\search_replace.py", "source_location": "L149"}, {"caller_nid": "search_replace_searchreplacecontroller_format_pattern_error", "callee": "translate", "source_file": "app\\controllers\\search_replace.py", "source_location": "L150"}, {"caller_nid": "search_replace_searchreplacecontroller_on_undo_redo", "callee": "getattr", "source_file": "app\\controllers\\search_replace.py", "source_location": "L155"}, {"caller_nid": "search_replace_searchreplacecontroller_on_undo_redo", "callee": "strip", "source_file": "app\\controllers\\search_replace.py", "source_location": "L158"}, {"caller_nid": "search_replace_searchreplacecontroller_on_undo_redo", "callee": "text", "source_file": "app\\controllers\\search_replace.py", "source_location": "L158"}, {"caller_nid": "search_replace_searchreplacecontroller_iter_blocks", "callee": "getattr", "source_file": "app\\controllers\\search_replace.py", "source_location": "L171"}, {"caller_nid": "search_replace_searchreplacecontroller_iter_blocks", "callee": "getattr", "source_file": "app\\controllers\\search_replace.py", "source_location": "L172"}, {"caller_nid": "search_replace_searchreplacecontroller_iter_blocks", "callee": "getattr", "source_file": "app\\controllers\\search_replace.py", "source_location": "L173"}, {"caller_nid": "search_replace_searchreplacecontroller_iter_blocks", "callee": "getattr", "source_file": "app\\controllers\\search_replace.py", "source_location": "L174"}, {"caller_nid": "search_replace_searchreplacecontroller_iter_blocks", "callee": "set", "source_file": "app\\controllers\\search_replace.py", "source_location": "L177"}, {"caller_nid": "search_replace_searchreplacecontroller_iter_blocks", "callee": "hasattr", "source_file": "app\\controllers\\search_replace.py", "source_location": "L181"}, {"caller_nid": "search_replace_searchreplacecontroller_iter_blocks", "callee": "hasattr", "source_file": "app\\controllers\\search_replace.py", "source_location": "L182"}, {"caller_nid": "search_replace_searchreplacecontroller_iter_blocks", "callee": "viewport", "source_file": "app\\controllers\\search_replace.py", "source_location": "L183"}, {"caller_nid": "search_replace_searchreplacecontroller_iter_blocks", "callee": "boundingRect", "source_file": "app\\controllers\\search_replace.py", "source_location": "L185"}, {"caller_nid": "search_replace_searchreplacecontroller_iter_blocks", "callee": "mapToScene", "source_file": "app\\controllers\\search_replace.py", "source_location": "L185"}, {"caller_nid": "search_replace_searchreplacecontroller_iter_blocks", "callee": "rect", "source_file": "app\\controllers\\search_replace.py", "source_location": "L185"}, {"caller_nid": "search_replace_searchreplacecontroller_iter_blocks", "callee": "viewport", "source_file": "app\\controllers\\search_replace.py", "source_location": "L185"}, {"caller_nid": "search_replace_searchreplacecontroller_iter_blocks", "callee": "set", "source_file": "app\\controllers\\search_replace.py", "source_location": "L186"}, {"caller_nid": "search_replace_searchreplacecontroller_iter_blocks", "callee": "get_pages_for_scene_bounds", "source_file": "app\\controllers\\search_replace.py", "source_location": "L186"}, {"caller_nid": "search_replace_searchreplacecontroller_iter_blocks", "callee": "set", "source_file": "app\\controllers\\search_replace.py", "source_location": "L186"}, {"caller_nid": "search_replace_searchreplacecontroller_iter_blocks", "callee": "hasattr", "source_file": "app\\controllers\\search_replace.py", "source_location": "L187"}, {"caller_nid": "search_replace_searchreplacecontroller_iter_blocks", "callee": "set", "source_file": "app\\controllers\\search_replace.py", "source_location": "L189"}, {"caller_nid": "search_replace_searchreplacecontroller_iter_blocks", "callee": "get_visible_pages", "source_file": "app\\controllers\\search_replace.py", "source_location": "L189"}, {"caller_nid": "search_replace_searchreplacecontroller_iter_blocks", "callee": "set", "source_file": "app\\controllers\\search_replace.py", "source_location": "L189"}, {"caller_nid": "search_replace_searchreplacecontroller_iter_blocks", "callee": "set", "source_file": "app\\controllers\\search_replace.py", "source_location": "L191"}, {"caller_nid": "search_replace_searchreplacecontroller_iter_blocks", "callee": "sorted", "source_file": "app\\controllers\\search_replace.py", "source_location": "L197"}, {"caller_nid": "search_replace_searchreplacecontroller_iter_blocks", "callee": "len", "source_file": "app\\controllers\\search_replace.py", "source_location": "L198"}, {"caller_nid": "search_replace_searchreplacecontroller_iter_blocks", "callee": "get", "source_file": "app\\controllers\\search_replace.py", "source_location": "L201"}, {"caller_nid": "search_replace_searchreplacecontroller_iter_blocks", "callee": "get", "source_file": "app\\controllers\\search_replace.py", "source_location": "L202"}, {"caller_nid": "search_replace_searchreplacecontroller_iter_blocks", "callee": "enumerate", "source_file": "app\\controllers\\search_replace.py", "source_location": "L203"}, {"caller_nid": "search_replace_searchreplacecontroller_iter_blocks", "callee": "enumerate", "source_file": "app\\controllers\\search_replace.py", "source_location": "L210"}, {"caller_nid": "search_replace_searchreplacecontroller_iter_blocks", "callee": "getattr", "source_file": "app\\controllers\\search_replace.py", "source_location": "L217"}, {"caller_nid": "search_replace_searchreplacecontroller_iter_blocks", "callee": "save_current_image_state", "source_file": "app\\controllers\\search_replace.py", "source_location": "L219"}, {"caller_nid": "search_replace_searchreplacecontroller_iter_blocks", "callee": "get", "source_file": "app\\controllers\\search_replace.py", "source_location": "L224"}, {"caller_nid": "search_replace_searchreplacecontroller_iter_blocks", "callee": "get", "source_file": "app\\controllers\\search_replace.py", "source_location": "L225"}, {"caller_nid": "search_replace_searchreplacecontroller_iter_blocks", "callee": "enumerate", "source_file": "app\\controllers\\search_replace.py", "source_location": "L226"}, {"caller_nid": "search_replace_searchreplacecontroller_search", "callee": "len", "source_file": "app\\controllers\\search_replace.py", "source_location": "L234"}, {"caller_nid": "search_replace_searchreplacecontroller_search", "callee": "compile_search_pattern", "source_file": "app\\controllers\\search_replace.py", "source_location": "L237"}, {"caller_nid": "search_replace_searchreplacecontroller_search", "callee": "set_status", "source_file": "app\\controllers\\search_replace.py", "source_location": "L239"}, {"caller_nid": "search_replace_searchreplacecontroller_search", "callee": "translate", "source_file": "app\\controllers\\search_replace.py", "source_location": "L239"}, {"caller_nid": "search_replace_searchreplacecontroller_search", "callee": "set_results", "source_file": "app\\controllers\\search_replace.py", "source_location": "L240"}, {"caller_nid": "search_replace_searchreplacecontroller_search", "callee": "set", "source_file": "app\\controllers\\search_replace.py", "source_location": "L246"}, {"caller_nid": "search_replace_searchreplacecontroller_search", "callee": "find_matches_in_text", "source_file": "app\\controllers\\search_replace.py", "source_location": "L250"}, {"caller_nid": "search_replace_searchreplacecontroller_search", "callee": "add", "source_file": "app\\controllers\\search_replace.py", "source_location": "L253"}, {"caller_nid": "search_replace_searchreplacecontroller_search", "callee": "enumerate", "source_file": "app\\controllers\\search_replace.py", "source_location": "L254"}, {"caller_nid": "search_replace_searchreplacecontroller_search", "callee": "build_block_key", "source_file": "app\\controllers\\search_replace.py", "source_location": "L255"}, {"caller_nid": "search_replace_searchreplacecontroller_search", "callee": "append", "source_file": "app\\controllers\\search_replace.py", "source_location": "L256"}, {"caller_nid": "search_replace_searchreplacecontroller_search", "callee": "SearchMatch", "source_file": "app\\controllers\\search_replace.py", "source_location": "L257"}, {"caller_nid": "search_replace_searchreplacecontroller_search", "callee": "_make_preview", "source_file": "app\\controllers\\search_replace.py", "source_location": "L263"}, {"caller_nid": "search_replace_searchreplacecontroller_search", "callee": "next", "source_file": "app\\controllers\\search_replace.py", "source_location": "L271"}, {"caller_nid": "search_replace_searchreplacecontroller_search", "callee": "enumerate", "source_file": "app\\controllers\\search_replace.py", "source_location": "L273"}, {"caller_nid": "search_replace_searchreplacecontroller_search", "callee": "set_results", "source_file": "app\\controllers\\search_replace.py", "source_location": "L286"}, {"caller_nid": "search_replace_searchreplacecontroller_search", "callee": "len", "source_file": "app\\controllers\\search_replace.py", "source_location": "L286"}, {"caller_nid": "search_replace_searchreplacecontroller_search", "callee": "len", "source_file": "app\\controllers\\search_replace.py", "source_location": "L286"}, {"caller_nid": "search_replace_searchreplacecontroller_search", "callee": "set_status", "source_file": "app\\controllers\\search_replace.py", "source_location": "L288"}, {"caller_nid": "search_replace_searchreplacecontroller_search", "callee": "translate", "source_file": "app\\controllers\\search_replace.py", "source_location": "L288"}, {"caller_nid": "search_replace_searchreplacecontroller_search", "callee": "hasFocus", "source_file": "app\\controllers\\search_replace.py", "source_location": "L291"}, {"caller_nid": "search_replace_searchreplacecontroller_search", "callee": "hasFocus", "source_file": "app\\controllers\\search_replace.py", "source_location": "L291"}, {"caller_nid": "search_replace_searchreplacecontroller_search", "callee": "_jump_to_match", "source_file": "app\\controllers\\search_replace.py", "source_location": "L292"}, {"caller_nid": "search_replace_searchreplacecontroller_search", "callee": "select_match", "source_file": "app\\controllers\\search_replace.py", "source_location": "L299"}, {"caller_nid": "search_replace_searchreplacecontroller_search", "callee": "set_status", "source_file": "app\\controllers\\search_replace.py", "source_location": "L301"}, {"caller_nid": "search_replace_searchreplacecontroller_search", "callee": "translate", "source_file": "app\\controllers\\search_replace.py", "source_location": "L301"}, {"caller_nid": "search_replace_searchreplacecontroller_next_match", "callee": "len", "source_file": "app\\controllers\\search_replace.py", "source_location": "L306"}, {"caller_nid": "search_replace_searchreplacecontroller_next_match", "callee": "hasFocus", "source_file": "app\\controllers\\search_replace.py", "source_location": "L309"}, {"caller_nid": "search_replace_searchreplacecontroller_next_match", "callee": "hasFocus", "source_file": "app\\controllers\\search_replace.py", "source_location": "L309"}, {"caller_nid": "search_replace_searchreplacecontroller_next_match", "callee": "_jump_to_match", "source_file": "app\\controllers\\search_replace.py", "source_location": "L310"}, {"caller_nid": "search_replace_searchreplacecontroller_prev_match", "callee": "len", "source_file": "app\\controllers\\search_replace.py", "source_location": "L317"}, {"caller_nid": "search_replace_searchreplacecontroller_prev_match", "callee": "hasFocus", "source_file": "app\\controllers\\search_replace.py", "source_location": "L320"}, {"caller_nid": "search_replace_searchreplacecontroller_prev_match", "callee": "hasFocus", "source_file": "app\\controllers\\search_replace.py", "source_location": "L320"}, {"caller_nid": "search_replace_searchreplacecontroller_prev_match", "callee": "_jump_to_match", "source_file": "app\\controllers\\search_replace.py", "source_location": "L321"}]}