{"nodes": [{"id": "modules_utils_platform_utils_py", "label": "platform_utils.py", "file_type": "code", "source_file": "modules\\utils\\platform_utils.py", "source_location": "L1"}, {"id": "platform_utils_get_client_os", "label": "get_client_os()", "file_type": "code", "source_file": "modules\\utils\\platform_utils.py", "source_location": "L6"}, {"id": "platform_utils_rationale_7", "label": "Returns the operating system name (e.g., 'Windows', 'Darwin' (macOS), 'Linux').", "file_type": "rationale", "source_file": "modules\\utils\\platform_utils.py", "source_location": "L7"}], "edges": [{"source": "modules_utils_platform_utils_py", "target": "platform", "relation": "imports", "confidence": "EXTRACTED", "source_file": "modules\\utils\\platform_utils.py", "source_location": "L1", "weight": 1.0}, {"source": "modules_utils_platform_utils_py", "target": "logging", "relation": "imports", "confidence": "EXTRACTED", "source_file": "modules\\utils\\platform_utils.py", "source_location": "L2", "weight": 1.0}, {"source": "modules_utils_platform_utils_py", "target": "platform_utils_get_client_os", "relation": "contains", "confidence": "EXTRACTED", "source_file": "modules\\utils\\platform_utils.py", "source_location": "L6", "weight": 1.0}, {"source": "platform_utils_rationale_7", "target": "platform_utils_get_client_os", "relation": "rationale_for", "confidence": "EXTRACTED", "source_file": "modules\\utils\\platform_utils.py", "source_location": "L7", "weight": 1.0}], "raw_calls": [{"caller_nid": "platform_utils_get_client_os", "callee": "system", "source_file": "modules\\utils\\platform_utils.py", "source_location": "L11"}, {"caller_nid": "platform_utils_get_client_os", "callee": "error", "source_file": "modules\\utils\\platform_utils.py", "source_location": "L16"}]}